{"facebook_page.107289372622044_1646192745398358":{"startingQuantum":4975784,"totalEngagement":1,"engagementVsAverage":0.004,"engagementVsMax":0,"engagementVsNetworkAverage":0.002,"enagementVsNetworkMax":0,"engagementVsScopeAverage":0.018,"engagementVsScopeMax":0},"facebook_page.107289372622044_1649300128420953":{"startingQuantum":4975784,"totalEngagement":160,"engagementVsAverage":0.673,"engagementVsMax":0.001,"engagementVsNetworkAverage":0.274,"enagementVsNetworkMax":0.001,"engagementVsScopeAverage":2.881,"engagementVsScopeMax":0.002},"facebook_page.107289372622044_1649526665064966":{"startingQuantum":4975784,"totalEngagement":74,"engagementVsAverage":0.311,"engagementVsMax":0,"engagementVsNetworkAverage":0.127,"enagementVsNetworkMax":0,"engagementVsScopeAverage":1.332,"engagementVsScopeMax":0.001},"facebook_page.107289372622044_1650778748273091":{"startingQuantum":4975784,"totalEngagement":0,"engagementVsAverage":0,"engagementVsMax":0,"engagementVsNetworkAverage":0,"enagementVsNetworkMax":0,"engagementVsScopeAverage":0,"engagementVsScopeMax":0},"facebook_page.107289372622044_1652565118094454":{"startingQuantum":4975784,"totalEngagement":17,"engagementVsAverage":0.071,"engagementVsMax":0,"engagementVsNetworkAverage":0.029,"enagementVsNetworkMax":0,"engagementVsScopeAverage":0.306,"engagementVsScopeMax":0},"facebook_page.107289372622044_1932112440402280":{"startingQuantum":4975784,"totalEngagement":2,"engagementVsAverage":0.008,"engagementVsMax":0,"engagementVsNetworkAverage":0.003,"enagementVsNetworkMax":0,"engagementVsScopeAverage":0.036,"engagementVsScopeMax":0},"facebook_page.107289372622044_1655265497824416":{"startingQuantum":4975784,"totalEngagement":104,"engagementVsAverage":0.437,"engagementVsMax":0.001,"engagementVsNetworkAverage":0.178,"enagementVsNetworkMax":0.001,"engagementVsScopeAverage":1.873,"engagementVsScopeMax":0.002},"facebook_page.107289372622044_1656297721054527":{"startingQuantum":4975784,"totalEngagement":6,"engagementVsAverage":0.025,"engagementVsMax":0,"engagementVsNetworkAverage":0.01,"enagementVsNetworkMax":0,"engagementVsScopeAverage":0.108,"engagementVsScopeMax":0},"facebook_page.107289372622044_1660538423963790":{"startingQuantum":4975784,"totalEngagement":28,"engagementVsAverage":0.118,"engagementVsMax":0,"engagementVsNetworkAverage":0.048,"enagementVsNetworkMax":0,"engagementVsScopeAverage":0.504,"engagementVsScopeMax":0},"facebook_page.107289372622044_1661458657205100":{"startingQuantum":4975784,"totalEngagement":2,"engagementVsAverage":0.008,"engagementVsMax":0,"engagementVsNetworkAverage":0.003,"enagementVsNetworkMax":0,"engagementVsScopeAverage":0.036,"engagementVsScopeMax":0},"facebook_page.107289372622044_1661462967204669":{"startingQuantum":4975784,"totalEngagement":12,"engagementVsAverage":0.05,"engagementVsMax":0,"engagementVsNetworkAverage":0.021,"enagementVsNetworkMax":0,"engagementVsScopeAverage":0.216,"engagementVsScopeMax":0},"facebook_page.107289372622044_1661494903868142":{"startingQuantum":4975784,"totalEngagement":4,"engagementVsAverage":0.017,"engagementVsMax":0,"engagementVsNetworkAverage":0.007,"enagementVsNetworkMax":0,"engagementVsScopeAverage":0.072,"engagementVsScopeMax":0},"facebook_page.107289372622044_1661861580498141":{"startingQuantum":4975784,"totalEngagement":0,"engagementVsAverage":0,"engagementVsMax":0,"engagementVsNetworkAverage":0,"enagementVsNetworkMax":0,"engagementVsScopeAverage":0,"engagementVsScopeMax":0},"facebook_page.107289372622044_1661964363821196":{"startingQuantum":4975784,"totalEngagement":12,"engagementVsAverage":0.05,"engagementVsMax":0,"engagementVsNetworkAverage":0.021,"enagementVsNetworkMax":0,"engagementVsScopeAverage":0.216,"engagementVsScopeMax":0},"facebook_page.107289372622044_1662714583746174":{"startingQuantum":4975784,"totalEngagement":76,"engagementVsAverage":0.32,"engagementVsMax":0.001,"engagementVsNetworkAverage":0.13,"enagementVsNetworkMax":0.001,"engagementVsScopeAverage":1.368,"engagementVsScopeMax":0.001},"facebook_page.107289372622044_1664499390234360":{"startingQuantum":4975784,"totalEngagement":15,"engagementVsAverage":0.063,"engagementVsMax":0,"engagementVsNetworkAverage":0.026,"enagementVsNetworkMax":0,"engagementVsScopeAverage":0.27,"engagementVsScopeMax":0},"facebook_page.107289372622044_1664581243559508":{"startingQuantum":4975784,"totalEngagement":4,"engagementVsAverage":0.017,"engagementVsMax":0,"engagementVsNetworkAverage":0.007,"enagementVsNetworkMax":0,"engagementVsScopeAverage":0.072,"engagementVsScopeMax":0},"facebook_page.107289372622044_1666306573386975":{"startingQuantum":4975784,"totalEngagement":5,"engagementVsAverage":0.021,"engagementVsMax":0,"engagementVsNetworkAverage":0.009,"enagementVsNetworkMax":0,"engagementVsScopeAverage":0.09,"engagementVsScopeMax":0},"facebook_page.107289372622044_1666479213369711":{"startingQuantum":4975784,"totalEngagement":66,"engagementVsAverage":0.278,"engagementVsMax":0,"engagementVsNetworkAverage":0.113,"enagementVsNetworkMax":0,"engagementVsScopeAverage":1.188,"engagementVsScopeMax":0.001},"facebook_page.107289372622044_1666571726693793":{"startingQuantum":4975784,"totalEngagement":41,"engagementVsAverage":0.172,"engagementVsMax":0,"engagementVsNetworkAverage":0.07,"enagementVsNetworkMax":0,"engagementVsScopeAverage":0.738,"engagementVsScopeMax":0.001},"facebook_page.107289372622044_1672330839451215":{"startingQuantum":4975784,"totalEngagement":12,"engagementVsAverage":0.05,"engagementVsMax":0,"engagementVsNetworkAverage":0.021,"enagementVsNetworkMax":0,"engagementVsScopeAverage":0.216,"engagementVsScopeMax":0},"facebook_page.107289372622044_1673344076016558":{"startingQuantum":4975784,"totalEngagement":172,"engagementVsAverage":0.723,"engagementVsMax":0.001,"engagementVsNetworkAverage":0.294,"enagementVsNetworkMax":0.001,"engagementVsScopeAverage":3.097,"engagementVsScopeMax":0.003},"facebook_page.107289372622044_1676275725723393":{"startingQuantum":4975784,"totalEngagement":11,"engagementVsAverage":0.046,"engagementVsMax":0,"engagementVsNetworkAverage":0.019,"enagementVsNetworkMax":0,"engagementVsScopeAverage":0.198,"engagementVsScopeMax":0},"facebook_page.107289372622044_1680011945349771":{"startingQuantum":4975784,"totalEngagement":12,"engagementVsAverage":0.05,"engagementVsMax":0,"engagementVsNetworkAverage":0.021,"enagementVsNetworkMax":0,"engagementVsScopeAverage":0.216,"engagementVsScopeMax":0},"facebook_page.107289372622044_1681722091845423":{"startingQuantum":4975784,"totalEngagement":6,"engagementVsAverage":0.025,"engagementVsMax":0,"engagementVsNetworkAverage":0.01,"enagementVsNetworkMax":0,"engagementVsScopeAverage":0.108,"engagementVsScopeMax":0},"facebook_page.107289372622044_1683090555041910":{"startingQuantum":4975784,"totalEngagement":98,"engagementVsAverage":0.412,"engagementVsMax":0.001,"engagementVsNetworkAverage":0.168,"enagementVsNetworkMax":0.001,"engagementVsScopeAverage":1.765,"engagementVsScopeMax":0.001},"facebook_page.107289372622044_1683585401659092":{"startingQuantum":4975784,"totalEngagement":243,"engagementVsAverage":1.022,"engagementVsMax":0.002,"engagementVsNetworkAverage":0.416,"enagementVsNetworkMax":0.002,"engagementVsScopeAverage":4.376,"engagementVsScopeMax":0.004},"facebook_page.107289372622044_1683679968316302":{"startingQuantum":4975784,"totalEngagement":200,"engagementVsAverage":0.841,"engagementVsMax":0.001,"engagementVsNetworkAverage":0.342,"enagementVsNetworkMax":0.001,"engagementVsScopeAverage":3.601,"engagementVsScopeMax":0.003},"facebook_page.107289372622044_1684754508208848":{"startingQuantum":4975784,"totalEngagement":164,"engagementVsAverage":0.69,"engagementVsMax":0.001,"engagementVsNetworkAverage":0.281,"enagementVsNetworkMax":0.001,"engagementVsScopeAverage":2.953,"engagementVsScopeMax":0.002},"facebook_page.107289372622044_1684814001536232":{"startingQuantum":4975784,"totalEngagement":15,"engagementVsAverage":0.063,"engagementVsMax":0,"engagementVsNetworkAverage":0.026,"enagementVsNetworkMax":0,"engagementVsScopeAverage":0.27,"engagementVsScopeMax":0},"facebook_page.107289372622044_1685008634850102":{"startingQuantum":4975784,"totalEngagement":4,"engagementVsAverage":0.017,"engagementVsMax":0,"engagementVsNetworkAverage":0.007,"enagementVsNetworkMax":0,"engagementVsScopeAverage":0.072,"engagementVsScopeMax":0},"facebook_page.107289372622044_1685087234842242":{"startingQuantum":4975784,"totalEngagement":73,"engagementVsAverage":0.307,"engagementVsMax":0,"engagementVsNetworkAverage":0.125,"enagementVsNetworkMax":0,"engagementVsScopeAverage":1.314,"engagementVsScopeMax":0.001},"facebook_page.107289372622044_1686396788044620":{"startingQuantum":4975784,"totalEngagement":15,"engagementVsAverage":0.063,"engagementVsMax":0,"engagementVsNetworkAverage":0.026,"enagementVsNetworkMax":0,"engagementVsScopeAverage":0.27,"engagementVsScopeMax":0},"facebook_page.107289372622044_1687221404628825":{"startingQuantum":4975784,"totalEngagement":55,"engagementVsAverage":0.231,"engagementVsMax":0,"engagementVsNetworkAverage":0.094,"enagementVsNetworkMax":0,"engagementVsScopeAverage":0.99,"engagementVsScopeMax":0.001},"facebook_page.107289372622044_1687428841274748":{"startingQuantum":4975784,"totalEngagement":3,"engagementVsAverage":0.013,"engagementVsMax":0,"engagementVsNetworkAverage":0.005,"enagementVsNetworkMax":0,"engagementVsScopeAverage":0.054,"engagementVsScopeMax":0},"facebook_page.107289372622044_1687692044581761":{"startingQuantum":4975784,"totalEngagement":60,"engagementVsAverage":0.252,"engagementVsMax":0,"engagementVsNetworkAverage":0.103,"enagementVsNetworkMax":0,"engagementVsScopeAverage":1.08,"engagementVsScopeMax":0.001},"facebook_page.107289372622044_1688563467827952":{"startingQuantum":4975784,"totalEngagement":17,"engagementVsAverage":0.071,"engagementVsMax":0,"engagementVsNetworkAverage":0.029,"enagementVsNetworkMax":0,"engagementVsScopeAverage":0.306,"engagementVsScopeMax":0},"facebook_page.107289372622044_1688693874481578":{"startingQuantum":4975784,"totalEngagement":9,"engagementVsAverage":0.038,"engagementVsMax":0,"engagementVsNetworkAverage":0.015,"enagementVsNetworkMax":0,"engagementVsScopeAverage":0.162,"engagementVsScopeMax":0},"facebook_page.107289372622044_1688765754474390":{"startingQuantum":4975784,"totalEngagement":447,"engagementVsAverage":1.88,"engagementVsMax":0.003,"engagementVsNetworkAverage":0.765,"enagementVsNetworkMax":0.003,"engagementVsScopeAverage":8.049,"engagementVsScopeMax":0.007},"facebook_page.107289372622044_1689855407698758":{"startingQuantum":4975784,"totalEngagement":86,"engagementVsAverage":0.362,"engagementVsMax":0.001,"engagementVsNetworkAverage":0.147,"enagementVsNetworkMax":0.001,"engagementVsScopeAverage":1.549,"engagementVsScopeMax":0.001}}