[{"content":"My surprise bridal shower and bachelorette party - thought I was going to my mom and future mom in law's birthday party but.... ❤️❤️❤️","profileString":"instagram.1782681231","postURL":"https://www.instagram.com/p/BU5JpdfgnKj/","avatar":"https://scontent.cdninstagram.com/t51.2885-19/s150x150/18252427_1853103164951663_40942755001663488_a.jpg","classification":{"engine":"aylien","language":"en","taxonomy":[{"score":"0.3654","confident":false,"links":[{"link":"https://api.aylien.com/api/v1/classify/taxonomy/iab-qag/IAB11-5","rel":"self"},{"link":"https://api.aylien.com/api/v1/classify/taxonomy/iab-qag/IAB11","rel":"parent"}],"id":"IAB11-5","label":"Commentary"},{"score":"0.1031","confident":true,"links":[{"link":"https://api.aylien.com/api/v1/classify/taxonomy/iab-qag/IAB11","rel":"self"}],"id":"IAB11","label":"Law, Gov’t & Politics"}]},"postidString":"instagram.1529295980053295779_1782681231","postMeta":{"inserted":"content-engine"},"timestamp":1496526309,"likesRcvd":176,"source":"instagram","lastUpdateQuantum":4995828,"name":"Juliet Huddy","repliesRcvd":14,"image":"https://scontent.cdninstagram.com/t51.2885-15/s640x640/sh0.08/e35/18812068_1862539937341433_2553073571723214848_n.jpg","username":"juliethuddytv","timeQuantum":4988421,"tags":[],"type":"photo"},{"content":"👍🏻👍🏻👍🏻","profileString":"instagram.1782681231","postURL":"https://www.instagram.com/p/BVIOk2ega01/","avatar":"https://scontent.cdninstagram.com/t51.2885-19/s150x150/18252427_1853103164951663_40942755001663488_a.jpg","classification":{"engine":"aylien","language":"en","taxonomy":[{"score":"0.0741","confident":false,"links":[{"link":"https://api.aylien.com/api/v1/classify/taxonomy/iab-qag/IAB9","rel":"self"}],"id":"IAB9","label":"Hobbies & Interests"},{"score":"0.0515","confident":false,"links":[{"link":"https://api.aylien.com/api/v1/classify/taxonomy/iab-qag/IAB9-4","rel":"self"},{"link":"https://api.aylien.com/api/v1/classify/taxonomy/iab-qag/IAB9","rel":"parent"}],"id":"IAB9-4","label":"Birdwatching"}]},"postidString":"instagram.1533539778165845301_1782681231","postMeta":{"inserted":"content-engine"},"timestamp":1497032209,"likesRcvd":37,"source":"instagram","lastUpdateQuantum":4995828,"name":"Juliet Huddy","repliesRcvd":2,"image":"https://scontent.cdninstagram.com/t51.2885-15/s640x640/sh0.08/e35/18949822_441766719532154_2905831154277941248_n.jpg","username":"juliethuddytv","timeQuantum":4990107,"tags":[],"type":"photo"},{"content":"💕💕💕💕💕💕💕💕💕","profileString":"instagram.1782681231","postURL":"https://www.instagram.com/p/BVLF7hZAn4f/","avatar":"https://scontent.cdninstagram.com/t51.2885-19/s150x150/18252427_1853103164951663_40942755001663488_a.jpg","classification":{"engine":"aylien","language":"en","taxonomy":[{"score":"0.0741","confident":false,"links":[{"link":"https://api.aylien.com/api/v1/classify/taxonomy/iab-qag/IAB9","rel":"self"}],"id":"IAB9","label":"Hobbies & Interests"},{"score":"0.0515","confident":false,"links":[{"link":"https://api.aylien.com/api/v1/classify/taxonomy/iab-qag/IAB9-4","rel":"self"},{"link":"https://api.aylien.com/api/v1/classify/taxonomy/iab-qag/IAB9","rel":"parent"}],"id":"IAB9-4","label":"Birdwatching"}]},"postidString":"instagram.1534346178584542751_1782681231","postMeta":{"inserted":"content-engine"},"timestamp":1497128339,"likesRcvd":56,"source":"instagram","lastUpdateQuantum":4995828,"name":"Juliet Huddy","repliesRcvd":1,"image":"https://scontent.cdninstagram.com/t51.2885-15/s640x640/sh0.08/e35/19051678_1285598418219358_3497823612130295808_n.jpg","username":"juliethuddytv","timeQuantum":4990427,"tags":[],"type":"photo"},{"content":"The cuteness factor is off the charts today.","profileString":"instagram.1782681231","postURL":"https://www.instagram.com/p/BVLGDllgLlN/","avatar":"https://scontent.cdninstagram.com/t51.2885-19/s150x150/18252427_1853103164951663_40942755001663488_a.jpg","classification":{"engine":"aylien","language":"en","taxonomy":[{"score":"0.0652","confident":false,"links":[{"link":"https://api.aylien.com/api/v1/classify/taxonomy/iab-qag/IAB9","rel":"self"}],"id":"IAB9","label":"Hobbies & Interests"},{"score":"0.0535","confident":false,"links":[{"link":"https://api.aylien.com/api/v1/classify/taxonomy/iab-qag/IAB9-9","rel":"self"},{"link":"https://api.aylien.com/api/v1/classify/taxonomy/iab-qag/IAB9","rel":"parent"}],"id":"IAB9-9","label":"Cigars"},{"score":"0.0532","confident":false,"links":[{"link":"https://api.aylien.com/api/v1/classify/taxonomy/iab-qag/IAB17","rel":"self"}],"id":"IAB17","label":"Sports"},{"score":"0.0447","confident":false,"links":[{"link":"https://api.aylien.com/api/v1/classify/taxonomy/iab-qag/IAB17-43","rel":"self"},{"link":"https://api.aylien.com/api/v1/classify/taxonomy/iab-qag/IAB17","rel":"parent"}],"id":"IAB17-43","label":"Waterski/Wakeboard"}]},"postidString":"instagram.1534346732844923213_1782681231","postMeta":{"inserted":"content-engine"},"timestamp":1497128405,"likesRcvd":83,"source":"instagram","lastUpdateQuantum":4995828,"name":"Juliet Huddy","repliesRcvd":1,"image":"https://scontent.cdninstagram.com/t51.2885-15/s640x640/sh0.08/e35/18949715_1930552950549536_1640481867016699904_n.jpg","username":"juliethuddytv","timeQuantum":4990428,"tags":[],"type":"photo"},{"content":"Oh well.  Was nice while it lasted.","profileString":"instagram.1782681231","postURL":"https://www.instagram.com/p/BVLlN3ZAGwH/","avatar":"https://scontent.cdninstagram.com/t51.2885-19/s150x150/18252427_1853103164951663_40942755001663488_a.jpg","classification":{"engine":"aylien","language":"en","taxonomy":[{"score":"0.0706","confident":false,"links":[{"link":"https://api.aylien.com/api/v1/classify/taxonomy/iab-qag/IAB9","rel":"self"}],"id":"IAB9","label":"Hobbies & Interests"},{"score":"0.0479","confident":false,"links":[{"link":"https://api.aylien.com/api/v1/classify/taxonomy/iab-qag/IAB9-4","rel":"self"},{"link":"https://api.aylien.com/api/v1/classify/taxonomy/iab-qag/IAB9","rel":"parent"}],"id":"IAB9-4","label":"Birdwatching"}]},"postidString":"instagram.1534483778599152647_1782681231","postMeta":{"inserted":"content-engine"},"timestamp":1497144742,"likesRcvd":52,"source":"instagram","lastUpdateQuantum":4995828,"name":"Juliet Huddy","repliesRcvd":5,"image":"https://scontent.cdninstagram.com/t51.2885-15/s640x640/sh0.08/e35/19050741_309109756208458_3147173131941052416_n.jpg","username":"juliethuddytv","timeQuantum":4990482,"tags":[],"type":"photo"},{"content":"Happy bday to my soon to be mama in law ❤️","profileString":"instagram.1782681231","postURL":"https://www.instagram.com/p/BVLlCffAsRX/","avatar":"https://scontent.cdninstagram.com/t51.2885-19/s150x150/18252427_1853103164951663_40942755001663488_a.jpg","classification":{"engine":"aylien","language":"en","taxonomy":[{"score":"0.5482","confident":true,"links":[{"link":"https://api.aylien.com/api/v1/classify/taxonomy/iab-qag/IAB11-5","rel":"self"},{"link":"https://api.aylien.com/api/v1/classify/taxonomy/iab-qag/IAB11","rel":"parent"}],"id":"IAB11-5","label":"Commentary"},{"score":"0.3593","confident":false,"links":[{"link":"https://api.aylien.com/api/v1/classify/taxonomy/iab-qag/IAB26-4","rel":"self"},{"link":"https://api.aylien.com/api/v1/classify/taxonomy/iab-qag/IAB26","rel":"parent"}],"id":"IAB26-4","label":"Copyright Infringement"},{"score":"0.1971","confident":false,"links":[{"link":"https://api.aylien.com/api/v1/classify/taxonomy/iab-qag/IAB25-2","rel":"self"},{"link":"https://api.aylien.com/api/v1/classify/taxonomy/iab-qag/IAB25","rel":"parent"}],"id":"IAB25-2","label":"Extreme Graphic/Explicit Violence"},{"score":"0.0638","confident":false,"links":[{"link":"https://api.aylien.com/api/v1/classify/taxonomy/iab-qag/IAB11","rel":"self"}],"id":"IAB11","label":"Law, Gov’t & Politics"},{"score":"0.0619","confident":false,"links":[{"link":"https://api.aylien.com/api/v1/classify/taxonomy/iab-qag/IAB9","rel":"self"}],"id":"IAB9","label":"Hobbies & Interests"},{"score":"0.0564","confident":false,"links":[{"link":"https://api.aylien.com/api/v1/classify/taxonomy/iab-qag/IAB25","rel":"self"}],"id":"IAB25","label":"Non-Standard Content"},{"score":"0.0527","confident":false,"links":[{"link":"https://api.aylien.com/api/v1/classify/taxonomy/iab-qag/IAB9-4","rel":"self"},{"link":"https://api.aylien.com/api/v1/classify/taxonomy/iab-qag/IAB9","rel":"parent"}],"id":"IAB9-4","label":"Birdwatching"},{"score":"0.0526","confident":false,"links":[{"link":"https://api.aylien.com/api/v1/classify/taxonomy/iab-qag/IAB26","rel":"self"}],"id":"IAB26","label":"Illegal Content"}]},"postidString":"instagram.1534482997015921751_1782681231","postMeta":{"inserted":"content-engine"},"timestamp":1497144649,"likesRcvd":94,"source":"instagram","lastUpdateQuantum":4995828,"name":"Juliet Huddy","repliesRcvd":2,"image":"https://scontent.cdninstagram.com/t51.2885-15/s640x640/sh0.08/e35/18949559_1490070091050203_6027903071412027392_n.jpg","username":"juliethuddytv","timeQuantum":4990482,"tags":[],"type":"photo"},{"content":"My little nephew in law ❤️","profileString":"instagram.1782681231","postURL":"https://www.instagram.com/p/BVPzyxrg4ET/","avatar":"https://scontent.cdninstagram.com/t51.2885-19/s150x150/18252427_1853103164951663_40942755001663488_a.jpg","classification":{"engine":"aylien","language":"en","taxonomy":[{"score":"0.5833","confident":true,"links":[{"link":"https://api.aylien.com/api/v1/classify/taxonomy/iab-qag/IAB11-5","rel":"self"},{"link":"https://api.aylien.com/api/v1/classify/taxonomy/iab-qag/IAB11","rel":"parent"}],"id":"IAB11-5","label":"Commentary"},{"score":"0.1169","confident":true,"links":[{"link":"https://api.aylien.com/api/v1/classify/taxonomy/iab-qag/IAB11","rel":"self"}],"id":"IAB11","label":"Law, Gov’t & Politics"}]},"postidString":"instagram.1535673787645919507_1782681231","postMeta":{"inserted":"content-engine"},"timestamp":1497286602,"likesRcvd":157,"source":"instagram","lastUpdateQuantum":4995828,"name":"Juliet Huddy","repliesRcvd":4,"image":"https://scontent.cdninstagram.com/t51.2885-15/s640x640/sh0.08/e35/19120607_1903324799915561_7138928187953643520_n.jpg","username":"juliethuddytv","timeQuantum":4990955,"tags":[],"type":"photo"},{"content":"Taken on our first date nearly two years ago.  And in one week from today - we're official. ❤️","profileString":"instagram.1782681231","postURL":"https://www.instagram.com/p/BVZ23pogHka/","avatar":"https://scontent.cdninstagram.com/t51.2885-19/s150x150/18252427_1853103164951663_40942755001663488_a.jpg","classification":{"engine":"aylien","language":"en","taxonomy":[{"score":"0.4424","confident":false,"links":[{"link":"https://api.aylien.com/api/v1/classify/taxonomy/iab-qag/IAB12-3","rel":"self"},{"link":"https://api.aylien.com/api/v1/classify/taxonomy/iab-qag/IAB12","rel":"parent"}],"id":"IAB12-3","label":"Local News"},{"score":"0.2962","confident":false,"links":[{"link":"https://api.aylien.com/api/v1/classify/taxonomy/iab-qag/IAB11-3","rel":"self"},{"link":"https://api.aylien.com/api/v1/classify/taxonomy/iab-qag/IAB11","rel":"parent"}],"id":"IAB11-3","label":"U.S. Government Resources"},{"score":"0.1923","confident":false,"links":[{"link":"https://api.aylien.com/api/v1/classify/taxonomy/iab-qag/IAB14-2","rel":"self"},{"link":"https://api.aylien.com/api/v1/classify/taxonomy/iab-qag/IAB14","rel":"parent"}],"id":"IAB14-2","label":"Divorce Support"},{"score":"0.0670","confident":false,"links":[{"link":"https://api.aylien.com/api/v1/classify/taxonomy/iab-qag/IAB20-14","rel":"self"},{"link":"https://api.aylien.com/api/v1/classify/taxonomy/iab-qag/IAB20","rel":"parent"}],"id":"IAB20-14","label":"Europe"},{"score":"0.0571","confident":false,"links":[{"link":"https://api.aylien.com/api/v1/classify/taxonomy/iab-qag/IAB17","rel":"self"}],"id":"IAB17","label":"Sports"},{"score":"0.0553","confident":false,"links":[{"link":"https://api.aylien.com/api/v1/classify/taxonomy/iab-qag/IAB11","rel":"self"}],"id":"IAB11","label":"Law, Gov’t & Politics"},{"score":"0.0509","confident":false,"links":[{"link":"https://api.aylien.com/api/v1/classify/taxonomy/iab-qag/IAB14","rel":"self"}],"id":"IAB14","label":"Society"},{"score":"0.0502","confident":false,"links":[{"link":"https://api.aylien.com/api/v1/classify/taxonomy/iab-qag/IAB12","rel":"self"}],"id":"IAB12","label":"News"},{"score":"0.0470","confident":false,"links":[{"link":"https://api.aylien.com/api/v1/classify/taxonomy/iab-qag/IAB20","rel":"self"}],"id":"IAB20","label":"Travel"},{"score":"0.0455","confident":false,"links":[{"link":"https://api.aylien.com/api/v1/classify/taxonomy/iab-qag/IAB17-44","rel":"self"},{"link":"https://api.aylien.com/api/v1/classify/taxonomy/iab-qag/IAB17","rel":"parent"}],"id":"IAB17-44","label":"World Soccer"}]},"postidString":"instagram.1538502066509478170_1782681231","postMeta":{"inserted":"content-engine"},"timestamp":1497623760,"likesRcvd":257,"source":"instagram","lastUpdateQuantum":4995828,"name":"Juliet Huddy","repliesRcvd":15,"image":"https://scontent.cdninstagram.com/t51.2885-15/e35/19120766_734448656734334_8596773288036794368_n.jpg","username":"juliethuddytv","timeQuantum":4992079,"tags":[],"type":"photo"},{"content":"My in laws ❤️","profileString":"instagram.1782681231","postURL":"https://www.instagram.com/p/BVxAAU-ghat/","avatar":"https://scontent.cdninstagram.com/t51.2885-19/s150x150/18252427_1853103164951663_40942755001663488_a.jpg","classification":{"engine":"aylien","language":"en","taxonomy":[{"score":"0.3036","links":[{"rel":"self","link":"https://api.aylien.com/api/v1/classify/taxonomy/iab-qag/IAB26-4"},{"rel":"parent","link":"https://api.aylien.com/api/v1/classify/taxonomy/iab-qag/IAB26"}],"label":"Copyright Infringement","id":"IAB26-4","confident":false},{"score":"0.1999","links":[{"rel":"self","link":"https://api.aylien.com/api/v1/classify/taxonomy/iab-qag/IAB25-2"},{"rel":"parent","link":"https://api.aylien.com/api/v1/classify/taxonomy/iab-qag/IAB25"}],"label":"Extreme Graphic/Explicit Violence","id":"IAB25-2","confident":false},{"score":"0.0779","links":[{"rel":"self","link":"https://api.aylien.com/api/v1/classify/taxonomy/iab-qag/IAB26"}],"label":"Illegal Content","id":"IAB26","confident":true},{"score":"0.0689","links":[{"rel":"self","link":"https://api.aylien.com/api/v1/classify/taxonomy/iab-qag/IAB25"}],"label":"Non-Standard Content","id":"IAB25","confident":false}]},"postidString":"instagram.1545016169688340141_1782681231","postMeta":{"inserted":"content-engine"},"timestamp":1498400301,"likesRcvd":221,"source":"instagram","lastUpdateQuantum":4995828,"name":"Juliet Huddy","repliesRcvd":5,"image":"https://scontent.cdninstagram.com/t51.2885-15/s640x640/sh0.08/e35/19424685_368910586858328_2759255181869711360_n.jpg","username":"juliethuddytv","timeQuantum":4994667,"tags":[],"type":"photo"},{"content":"Rain and giant construction cranes forced our ceremony inside - but it was still perfect ❤️","profileString":"instagram.1782681231","postURL":"https://www.instagram.com/p/BVxAKJ7AgOm/","avatar":"https://scontent.cdninstagram.com/t51.2885-19/s150x150/18252427_1853103164951663_40942755001663488_a.jpg","classification":{"engine":"aylien","language":"en","taxonomy":[{"score":"0.4534","links":[{"rel":"self","link":"https://api.aylien.com/api/v1/classify/taxonomy/iab-qag/IAB25-6"},{"rel":"parent","link":"https://api.aylien.com/api/v1/classify/taxonomy/iab-qag/IAB25"}],"label":"Under Construction","id":"IAB25-6","confident":true},{"score":"0.2025","links":[{"rel":"self","link":"https://api.aylien.com/api/v1/classify/taxonomy/iab-qag/IAB10-9"},{"rel":"parent","link":"https://api.aylien.com/api/v1/classify/taxonomy/iab-qag/IAB10"}],"label":"Remodeling & Construction","id":"IAB10-9","confident":false},{"score":"0.0690","links":[{"rel":"self","link":"https://api.aylien.com/api/v1/classify/taxonomy/iab-qag/IAB25"}],"label":"Non-Standard Content","id":"IAB25","confident":false},{"score":"0.0633","links":[{"rel":"self","link":"https://api.aylien.com/api/v1/classify/taxonomy/iab-qag/IAB9"}],"label":"Hobbies & Interests","id":"IAB9","confident":false},{"score":"0.0596","links":[{"rel":"self","link":"https://api.aylien.com/api/v1/classify/taxonomy/iab-qag/IAB10"}],"label":"Home & Garden","id":"IAB10","confident":false},{"score":"0.0520","links":[{"rel":"self","link":"https://api.aylien.com/api/v1/classify/taxonomy/iab-qag/IAB9-4"},{"rel":"parent","link":"https://api.aylien.com/api/v1/classify/taxonomy/iab-qag/IAB9"}],"label":"Birdwatching","id":"IAB9-4","confident":false}]},"postidString":"instagram.1545016845013222310_1782681231","postMeta":{"inserted":"content-engine"},"timestamp":1498400382,"likesRcvd":351,"source":"instagram","lastUpdateQuantum":4995828,"name":"Juliet Huddy","repliesRcvd":44,"image":"https://scontent.cdninstagram.com/t51.2885-15/s640x640/sh0.08/e35/19425496_206765953180896_1191557144911020032_n.jpg","username":"juliethuddytv","timeQuantum":4994667,"tags":[],"type":"photo"},{"content":"I think people should walk around in fairy lights every day. They're very becoming.","profileString":"instagram.1782681231","postURL":"https://www.instagram.com/p/BVxAQHjgypG/","avatar":"https://scontent.cdninstagram.com/t51.2885-19/s150x150/18252427_1853103164951663_40942755001663488_a.jpg","classification":{"engine":"aylien","language":"en","taxonomy":[{"score":"0.3227","links":[{"rel":"self","link":"https://api.aylien.com/api/v1/classify/taxonomy/iab-qag/IAB14-5"},{"rel":"parent","link":"https://api.aylien.com/api/v1/classify/taxonomy/iab-qag/IAB14"}],"label":"Senior Living","id":"IAB14-5","confident":true},{"score":"0.1222","links":[{"rel":"self","link":"https://api.aylien.com/api/v1/classify/taxonomy/iab-qag/IAB14"}],"label":"Society","id":"IAB14","confident":true}]},"postidString":"instagram.1545017254788409926_1782681231","postMeta":{"inserted":"content-engine"},"timestamp":1498400431,"likesRcvd":300,"source":"instagram","lastUpdateQuantum":4995828,"name":"Juliet Huddy","repliesRcvd":26,"image":"https://scontent.cdninstagram.com/t51.2885-15/s640x640/sh0.08/e35/19428789_164288780780414_3657367834561871872_n.jpg","username":"juliethuddytv","timeQuantum":4994668,"tags":[],"type":"photo"},{"content":"Family photo w the in-laws ❤️","profileString":"instagram.1782681231","postURL":"https://www.instagram.com/p/BVxWz5NgS_R/","avatar":"https://scontent.cdninstagram.com/t51.2885-19/s150x150/18252427_1853103164951663_40942755001663488_a.jpg","classification":{"engine":"aylien","language":"en","taxonomy":[{"score":"0.2202","links":[{"rel":"self","link":"https://api.aylien.com/api/v1/classify/taxonomy/iab-qag/IAB6-1"},{"rel":"parent","link":"https://api.aylien.com/api/v1/classify/taxonomy/iab-qag/IAB6"}],"label":"Adoption","id":"IAB6-1","confident":false},{"score":"0.2062","links":[{"rel":"self","link":"https://api.aylien.com/api/v1/classify/taxonomy/iab-qag/IAB6"}],"label":"Family & Parenting","id":"IAB6","confident":true}]},"postidString":"instagram.1545116470311202769_1782681231","postMeta":{"inserted":"content-engine"},"timestamp":1498412258,"likesRcvd":109,"source":"instagram","lastUpdateQuantum":4995828,"name":"Juliet Huddy","repliesRcvd":2,"image":"https://scontent.cdninstagram.com/t51.2885-15/s640x640/sh0.08/e35/c109.0.720.720/19379563_674212482768866_5551880919599546368_n.jpg","username":"juliethuddytv","timeQuantum":4994707,"tags":[],"type":"photo"},{"content":"Making my toast (and watching John have a near nervous breakdown in anticipation of having to give his) ❤️","profileString":"instagram.1782681231","postURL":"https://www.instagram.com/p/BVxWoGDgYil/","avatar":"https://scontent.cdninstagram.com/t51.2885-19/s150x150/18252427_1853103164951663_40942755001663488_a.jpg","classification":{"engine":"aylien","language":"en","taxonomy":[{"score":"0.0789","links":[{"rel":"self","link":"https://api.aylien.com/api/v1/classify/taxonomy/iab-qag/IAB9"}],"label":"Hobbies & Interests","id":"IAB9","confident":true},{"score":"0.0652","links":[{"rel":"self","link":"https://api.aylien.com/api/v1/classify/taxonomy/iab-qag/IAB9-4"},{"rel":"parent","link":"https://api.aylien.com/api/v1/classify/taxonomy/iab-qag/IAB9"}],"label":"Birdwatching","id":"IAB9-4","confident":false}]},"postidString":"instagram.1545115659468376229_1782681231","postMeta":{"inserted":"content-engine"},"timestamp":1498412161,"likesRcvd":167,"source":"instagram","lastUpdateQuantum":4995828,"name":"Juliet Huddy","repliesRcvd":6,"image":"https://scontent.cdninstagram.com/t51.2885-15/s640x640/sh0.08/e35/19379706_162738234268651_2190401490957369344_n.jpg","username":"juliethuddytv","timeQuantum":4994707,"tags":[],"type":"photo"},{"content":"Last pic of the night - I think it's clear it was quite a night!","profileString":"instagram.1782681231","postURL":"https://www.instagram.com/p/BVx2L_hgBDq/","avatar":"https://scontent.cdninstagram.com/t51.2885-19/s150x150/18252427_1853103164951663_40942755001663488_a.jpg","classification":{"engine":"aylien","language":"en","taxonomy":[{"score":"0.3128","links":[{"rel":"self","link":"https://api.aylien.com/api/v1/classify/taxonomy/iab-qag/IAB1-2"},{"rel":"parent","link":"https://api.aylien.com/api/v1/classify/taxonomy/iab-qag/IAB1"}],"label":"Celebrity Fan/Gossip","id":"IAB1-2","confident":true},{"score":"0.0740","links":[{"rel":"self","link":"https://api.aylien.com/api/v1/classify/taxonomy/iab-qag/IAB1"}],"label":"Arts & Entertainment","id":"IAB1","confident":false}]},"postidString":"instagram.1545254465798410474_1782681231","postMeta":{"inserted":"content-engine"},"timestamp":1498428708,"likesRcvd":385,"source":"instagram","lastUpdateQuantum":4995828,"name":"Juliet Huddy","repliesRcvd":28,"image":"https://scontent.cdninstagram.com/t51.2885-15/s640x640/sh0.08/e35/19429543_137513820158183_4306070654043553792_n.jpg","username":"juliethuddytv","timeQuantum":4994762,"tags":[],"type":"photo"},{"content":"❤️","profileString":"instagram.1782681231","postURL":"https://www.instagram.com/p/BVx9dI6Ae4R/","avatar":"https://scontent.cdninstagram.com/t51.2885-19/s150x150/18252427_1853103164951663_40942755001663488_a.jpg","classification":{"engine":"aylien","language":"en","taxonomy":[{"score":"0.0741","links":[{"rel":"self","link":"https://api.aylien.com/api/v1/classify/taxonomy/iab-qag/IAB9"}],"label":"Hobbies & Interests","id":"IAB9","confident":false},{"score":"0.0515","links":[{"rel":"self","link":"https://api.aylien.com/api/v1/classify/taxonomy/iab-qag/IAB9-4"},{"rel":"parent","link":"https://api.aylien.com/api/v1/classify/taxonomy/iab-qag/IAB9"}],"label":"Birdwatching","id":"IAB9-4","confident":false}]},"postidString":"instagram.1545286430429933073_1782681231","postMeta":{"inserted":"content-engine"},"timestamp":1498432519,"likesRcvd":190,"source":"instagram","lastUpdateQuantum":4995828,"name":"Juliet Huddy","repliesRcvd":15,"image":"https://scontent.cdninstagram.com/t51.2885-15/s640x640/sh0.08/e35/19424828_617340065142078_2381603539370639360_n.jpg","username":"juliethuddytv","timeQuantum":4994775,"tags":[],"type":"photo"},{"content":"Our wedding welcome meet and greet #SurfCityNJ #JerseyCity","profileString":"instagram.1782681231","postURL":"https://www.instagram.com/p/BVx_as3AQmK/","avatar":"https://scontent.cdninstagram.com/t51.2885-19/s150x150/18252427_1853103164951663_40942755001663488_a.jpg","classification":{"engine":"aylien","language":"en","taxonomy":[{"score":"0.6087","links":[{"rel":"self","link":"https://api.aylien.com/api/v1/classify/taxonomy/iab-qag/IAB14-7"},{"rel":"parent","link":"https://api.aylien.com/api/v1/classify/taxonomy/iab-qag/IAB14"}],"label":"Weddings","id":"IAB14-7","confident":true},{"score":"0.2624","links":[{"rel":"self","link":"https://api.aylien.com/api/v1/classify/taxonomy/iab-qag/IAB14"}],"label":"Society","id":"IAB14","confident":true}]},"postidString":"instagram.1545295058968840586_1782681231","postMeta":{"inserted":"content-engine"},"timestamp":1498433547,"likesRcvd":193,"source":"instagram","lastUpdateQuantum":4995828,"name":"Juliet Huddy","repliesRcvd":6,"image":"https://scontent.cdninstagram.com/t51.2885-15/s640x640/sh0.08/e35/19424761_1478094848917650_712743625133391872_n.jpg","username":"juliethuddytv","timeQuantum":4994778,"tags":["surfcitynj","jerseycity"],"type":"photo"},{"content":"With two of my favorite people in the world ❤️💕❤️💕","profileString":"instagram.1782681231","postURL":"https://www.instagram.com/p/BVx_fo3g0L7/","avatar":"https://scontent.cdninstagram.com/t51.2885-19/s150x150/18252427_1853103164951663_40942755001663488_a.jpg","classification":{"engine":"aylien","language":"en","taxonomy":[{"score":"0.5190","links":[{"rel":"self","link":"https://api.aylien.com/api/v1/classify/taxonomy/iab-qag/IAB14-5"},{"rel":"parent","link":"https://api.aylien.com/api/v1/classify/taxonomy/iab-qag/IAB14"}],"label":"Senior Living","id":"IAB14-5","confident":true},{"score":"0.2716","links":[{"rel":"self","link":"https://api.aylien.com/api/v1/classify/taxonomy/iab-qag/IAB14"}],"label":"Society","id":"IAB14","confident":true}]},"postidString":"instagram.1545295398279791355_1782681231","postMeta":{"inserted":"content-engine"},"timestamp":1498433588,"likesRcvd":219,"source":"instagram","lastUpdateQuantum":4995828,"name":"Juliet Huddy","repliesRcvd":4,"image":"https://scontent.cdninstagram.com/t51.2885-15/s640x640/sh0.08/e35/19424582_476320309376669_4176858972420046848_n.jpg","username":"juliethuddytv","timeQuantum":4994778,"tags":[],"type":"photo"},{"content":"BFF's ❤️💛💚💜","profileString":"instagram.1782681231","postURL":"https://www.instagram.com/p/BVx_oeAgQhL/","avatar":"https://scontent.cdninstagram.com/t51.2885-19/s150x150/18252427_1853103164951663_40942755001663488_a.jpg","classification":{"engine":"aylien","language":"en","taxonomy":[{"score":"0.2051","links":[{"rel":"self","link":"https://api.aylien.com/api/v1/classify/taxonomy/iab-qag/IAB25-2"},{"rel":"parent","link":"https://api.aylien.com/api/v1/classify/taxonomy/iab-qag/IAB25"}],"label":"Extreme Graphic/Explicit Violence","id":"IAB25-2","confident":false},{"score":"0.0724","links":[{"rel":"self","link":"https://api.aylien.com/api/v1/classify/taxonomy/iab-qag/IAB9"}],"label":"Hobbies & Interests","id":"IAB9","confident":false},{"score":"0.0599","links":[{"rel":"self","link":"https://api.aylien.com/api/v1/classify/taxonomy/iab-qag/IAB25"}],"label":"Non-Standard Content","id":"IAB25","confident":false},{"score":"0.0515","links":[{"rel":"self","link":"https://api.aylien.com/api/v1/classify/taxonomy/iab-qag/IAB9-4"},{"rel":"parent","link":"https://api.aylien.com/api/v1/classify/taxonomy/iab-qag/IAB9"}],"label":"Birdwatching","id":"IAB9-4","confident":false}]},"postidString":"instagram.1545296005094770763_1782681231","postMeta":{"inserted":"content-engine"},"timestamp":1498433660,"likesRcvd":112,"source":"instagram","lastUpdateQuantum":4995828,"name":"Juliet Huddy","repliesRcvd":4,"image":"https://scontent.cdninstagram.com/t51.2885-15/e35/c191.0.578.578/19533550_184640962069996_1838288050417827840_n.jpg","username":"juliethuddytv","timeQuantum":4994778,"tags":[],"type":"photo"},{"profileString":"instagram.1782681231","postURL":"https://www.instagram.com/p/BVx_soLgwkO/","avatar":"https://scontent.cdninstagram.com/t51.2885-19/s150x150/18252427_1853103164951663_40942755001663488_a.jpg","classification":{"engine":"aylien","language":"en","taxonomy":[{"score":0,"categoryId":"INSERTED","label":"News"}]},"postidString":"instagram.1545296290894776590_1782681231","postMeta":{"inserted":"content-engine"},"timestamp":1498433694,"likesRcvd":71,"source":"instagram","lastUpdateQuantum":4995828,"name":"Juliet Huddy","repliesRcvd":0,"image":"https://scontent.cdninstagram.com/t51.2885-15/e35/19436778_668868746637706_6380646746862649344_n.jpg","username":"juliethuddytv","timeQuantum":4994778,"tags":[],"type":"photo"},{"content":"Finally have a sister!","profileString":"instagram.1782681231","postURL":"https://www.instagram.com/p/BVyAEgrgSoo/","avatar":"https://scontent.cdninstagram.com/t51.2885-19/s150x150/18252427_1853103164951663_40942755001663488_a.jpg","classification":{"engine":"aylien","language":"en","taxonomy":[{"score":"0.2136","links":[{"rel":"self","link":"https://api.aylien.com/api/v1/classify/taxonomy/iab-qag/IAB1-2"},{"rel":"parent","link":"https://api.aylien.com/api/v1/classify/taxonomy/iab-qag/IAB1"}],"label":"Celebrity Fan/Gossip","id":"IAB1-2","confident":false},{"score":"0.2102","links":[{"rel":"self","link":"https://api.aylien.com/api/v1/classify/taxonomy/iab-qag/IAB25-4"},{"rel":"parent","link":"https://api.aylien.com/api/v1/classify/taxonomy/iab-qag/IAB25"}],"label":"Profane Content","id":"IAB25-4","confident":false},{"score":"0.0682","links":[{"rel":"self","link":"https://api.aylien.com/api/v1/classify/taxonomy/iab-qag/IAB25"}],"label":"Non-Standard Content","id":"IAB25","confident":false},{"score":"0.0644","links":[{"rel":"self","link":"https://api.aylien.com/api/v1/classify/taxonomy/iab-qag/IAB9"}],"label":"Hobbies & Interests","id":"IAB9","confident":false},{"score":"0.0568","links":[{"rel":"self","link":"https://api.aylien.com/api/v1/classify/taxonomy/iab-qag/IAB1"}],"label":"Arts & Entertainment","id":"IAB1","confident":false},{"score":"0.0550","links":[{"rel":"self","link":"https://api.aylien.com/api/v1/classify/taxonomy/iab-qag/IAB9-6"},{"rel":"parent","link":"https://api.aylien.com/api/v1/classify/taxonomy/iab-qag/IAB9"}],"label":"Candle & Soap Making","id":"IAB9-6","confident":false}]},"postidString":"instagram.1545297932109031976_1782681231","postMeta":{"inserted":"content-engine"},"timestamp":1498433890,"likesRcvd":84,"source":"instagram","lastUpdateQuantum":4995828,"name":"Juliet Huddy","repliesRcvd":1,"image":"https://scontent.cdninstagram.com/t51.2885-15/s640x640/sh0.08/e35/19379807_122728638236726_7830260220000468992_n.jpg","username":"juliethuddytv","timeQuantum":4994779,"tags":[],"type":"photo"},{"content":"Mr. and Mrs. Fattoruso 💚💛💜 6.23.17 #BigFattsLove #Battello #BestWeddingVenue","profileString":"instagram.1782681231","postURL":"https://www.instagram.com/p/BVx_9ZrgZib/","avatar":"https://scontent.cdninstagram.com/t51.2885-19/s150x150/18252427_1853103164951663_40942755001663488_a.jpg","classification":{"engine":"aylien","language":"en","taxonomy":[{"score":"0.0741","links":[{"rel":"self","link":"https://api.aylien.com/api/v1/classify/taxonomy/iab-qag/IAB9"}],"label":"Hobbies & Interests","id":"IAB9","confident":false},{"score":"0.0515","links":[{"rel":"self","link":"https://api.aylien.com/api/v1/classify/taxonomy/iab-qag/IAB9-4"},{"rel":"parent","link":"https://api.aylien.com/api/v1/classify/taxonomy/iab-qag/IAB9"}],"label":"Birdwatching","id":"IAB9-4","confident":false}]},"postidString":"instagram.1545297443556530331_1782681231","postMeta":{"inserted":"content-engine"},"timestamp":1498433832,"likesRcvd":96,"source":"instagram","lastUpdateQuantum":4995828,"name":"Juliet Huddy","repliesRcvd":2,"image":"https://scontent.cdninstagram.com/t51.2885-15/e35/19379940_1889075584679526_7963708783782264832_n.jpg","username":"juliethuddytv","timeQuantum":4994779,"tags":["battello","bigfattslove","bestweddingvenue"],"type":"photo"},{"content":"I quoted the beautifully written song \"Redshift\" by my faves @EnterShikariOfficial in my wedding toast.  My amazing new hubby and I will be 'drinking in the vistas' forever ❤️. Thank you @roureynolds for your beautiful lyrics.","profileString":"instagram.1782681231","postURL":"https://www.instagram.com/p/BVyDdWjgQc7/","avatar":"https://scontent.cdninstagram.com/t51.2885-19/s150x150/18252427_1853103164951663_40942755001663488_a.jpg","classification":{"engine":"aylien","language":"en","taxonomy":[{"score":"0.4170","links":[{"rel":"self","link":"https://api.aylien.com/api/v1/classify/taxonomy/iab-qag/IAB14-7"},{"rel":"parent","link":"https://api.aylien.com/api/v1/classify/taxonomy/iab-qag/IAB14"}],"label":"Weddings","id":"IAB14-7","confident":true},{"score":"0.0941","links":[{"rel":"self","link":"https://api.aylien.com/api/v1/classify/taxonomy/iab-qag/IAB14"}],"label":"Society","id":"IAB14","confident":true},{"score":"0.0795","links":[{"rel":"self","link":"https://api.aylien.com/api/v1/classify/taxonomy/iab-qag/IAB9"}],"label":"Hobbies & Interests","id":"IAB9","confident":true},{"score":"0.0527","links":[{"rel":"self","link":"https://api.aylien.com/api/v1/classify/taxonomy/iab-qag/IAB9-28"},{"rel":"parent","link":"https://api.aylien.com/api/v1/classify/taxonomy/iab-qag/IAB9"}],"label":"Screenwriting","id":"IAB9-28","confident":false}]},"postidString":"instagram.1545312833363838779_1782681231","postMeta":{"inserted":"content-engine"},"timestamp":1498435666,"likesRcvd":31,"source":"instagram","lastUpdateQuantum":4995828,"name":"Juliet Huddy","repliesRcvd":0,"image":"https://scontent.cdninstagram.com/t51.2885-15/s640x640/sh0.08/e35/19535030_330874230678693_6911904420074618880_n.jpg","username":"juliethuddytv","timeQuantum":4994785,"tags":[],"type":"photo"},{"content":"My two knockout Fox5-ers ❤️ @audreypuente @lidianews1","profileString":"instagram.1782681231","postURL":"https://www.instagram.com/p/BVyLooOAxSc/","avatar":"https://scontent.cdninstagram.com/t51.2885-19/s150x150/18252427_1853103164951663_40942755001663488_a.jpg","classification":{"engine":"aylien","language":"en","taxonomy":[{"score":"0.0729","links":[{"rel":"self","link":"https://api.aylien.com/api/v1/classify/taxonomy/iab-qag/IAB9"}],"label":"Hobbies & Interests","id":"IAB9","confident":false},{"score":"0.0515","links":[{"rel":"self","link":"https://api.aylien.com/api/v1/classify/taxonomy/iab-qag/IAB9-4"},{"rel":"parent","link":"https://api.aylien.com/api/v1/classify/taxonomy/iab-qag/IAB9"}],"label":"Birdwatching","id":"IAB9-4","confident":false}]},"postidString":"instagram.1545348792616948892_1782681231","postMeta":{"inserted":"content-engine"},"timestamp":1498439953,"likesRcvd":210,"source":"instagram","lastUpdateQuantum":4995828,"name":"Juliet Huddy","repliesRcvd":6,"image":"https://scontent.cdninstagram.com/t51.2885-15/s640x640/sh0.08/e35/c0.135.1080.1080/19533683_1586234181428934_5177254351416066048_n.jpg","username":"juliethuddytv","timeQuantum":4994799,"tags":[],"type":"photo"},{"content":"Love this shot 💛💜💚","profileString":"instagram.1782681231","postURL":"https://www.instagram.com/p/BVya4rPACBF/","avatar":"https://scontent.cdninstagram.com/t51.2885-19/s150x150/18252427_1853103164951663_40942755001663488_a.jpg","classification":{"engine":"aylien","language":"en","taxonomy":[{"score":"0.1091","links":[{"rel":"self","link":"https://api.aylien.com/api/v1/classify/taxonomy/iab-qag/IAB9"}],"label":"Hobbies & Interests","id":"IAB9","confident":true},{"score":"0.0652","links":[{"rel":"self","link":"https://api.aylien.com/api/v1/classify/taxonomy/iab-qag/IAB9-23"},{"rel":"parent","link":"https://api.aylien.com/api/v1/classify/taxonomy/iab-qag/IAB9"}],"label":"Photography","id":"IAB9-23","confident":false}]},"postidString":"instagram.1545415866064052293_1782681231","postMeta":{"inserted":"content-engine"},"timestamp":1498447949,"likesRcvd":94,"source":"instagram","lastUpdateQuantum":4995828,"name":"Juliet Huddy","repliesRcvd":0,"image":"https://scontent.cdninstagram.com/t51.2885-15/s640x640/sh0.08/e35/19380031_319501738494388_8312869137953062912_n.jpg","username":"juliethuddytv","timeQuantum":4994826,"tags":[],"type":"photo"},{"content":"Childhood pals 💝","profileString":"instagram.1782681231","postURL":"https://www.instagram.com/p/BVybHLzgpQp/","avatar":"https://scontent.cdninstagram.com/t51.2885-19/s150x150/18252427_1853103164951663_40942755001663488_a.jpg","classification":{"engine":"aylien","language":"en","taxonomy":[{"score":"0.0765","links":[{"rel":"self","link":"https://api.aylien.com/api/v1/classify/taxonomy/iab-qag/IAB9"}],"label":"Hobbies & Interests","id":"IAB9","confident":false},{"score":"0.0574","links":[{"rel":"self","link":"https://api.aylien.com/api/v1/classify/taxonomy/iab-qag/IAB9-9"},{"rel":"parent","link":"https://api.aylien.com/api/v1/classify/taxonomy/iab-qag/IAB9"}],"label":"Cigars","id":"IAB9-9","confident":false}]},"postidString":"instagram.1545416863108994089_1782681231","postMeta":{"inserted":"content-engine"},"timestamp":1498448068,"likesRcvd":88,"source":"instagram","lastUpdateQuantum":4995828,"name":"Juliet Huddy","repliesRcvd":0,"image":"https://scontent.cdninstagram.com/t51.2885-15/s640x640/sh0.08/e35/19533582_1904347963172303_8766859993027706880_n.jpg","username":"juliethuddytv","timeQuantum":4994826,"tags":[],"type":"photo"},{"content":"My besties from the ol college days #Mizzou #25Years #Roommates","profileString":"instagram.1782681231","postURL":"https://www.instagram.com/p/BV5YmJoAnqM/","avatar":"https://scontent.cdninstagram.com/t51.2885-19/s150x150/18252427_1853103164951663_40942755001663488_a.jpg","classification":{"engine":"aylien","language":"en","taxonomy":[{"score":"0.0710","links":[{"rel":"self","link":"https://api.aylien.com/api/v1/classify/taxonomy/iab-qag/IAB9"}],"label":"Hobbies & Interests","id":"IAB9","confident":false},{"score":"0.0498","links":[{"rel":"self","link":"https://api.aylien.com/api/v1/classify/taxonomy/iab-qag/IAB9-9"},{"rel":"parent","link":"https://api.aylien.com/api/v1/classify/taxonomy/iab-qag/IAB9"}],"label":"Cigars","id":"IAB9-9","confident":false}]},"postidString":"instagram.1547376121769785996_1782681231","postMeta":{"inserted":"content-engine"},"timestamp":1498681629,"likesRcvd":146,"source":"instagram","lastUpdateQuantum":4995828,"name":"Juliet Huddy","repliesRcvd":2,"image":"https://scontent.cdninstagram.com/t51.2885-15/s640x640/sh0.08/e35/19535437_453307571693673_2396688147413991424_n.jpg","username":"juliethuddytv","timeQuantum":4995605,"tags":["25years","mizzou","roommates"],"type":"photo"}]