{"scoreEntityString":"591d1494ab33fb0001804f89.asset.536575feb08f37d80186a099","timeQuantum":4984422,"scoreEntityType":"asset","scoreProfileID":"591d1494ab33fb0001804f89","data":{"scoreEntityString":"591d1494ab33fb0001804f89.asset.536575feb08f37d80186a099","scoreProfileID":"591d1494ab33fb0001804f89","scoreEntityType":"asset","entityID":"asset.536575feb08f37d80186a099","object_version":"1.2","score_engine_version":"3.0.19","timestamp":4984422,"start_quantum":4958502,"end_quantum":4984421,"schedule_options":{"interval":15,"offset":"1"},"_15min":{"boundaryQuantum":4984419,"combined":{"entityString":"536575feb08f37d80186a099","type":"combined","profiles":2,"postsMade":0,"repliesMade":0,"repliesRcvd":0,"sharesMade":0,"sharesRcvd":0,"mentionsRcvd":0,"likesRcvd":0,"reachRcvd":0,"audience":7916,"voice":0,"conversation":0,"engagement":0,"group_scoped":{"audienceScore":0.34750238150634116,"voiceScore":0,"engagementScore":0,"combinedScore":0.34750238150634116,"engagementSEI":0,"engagementSEIadj":0,"voiceSEI":0,"voiceSEIadj":0,"audienceSEI":0.5383334784122563,"audienceSEIadj":0.5383334784122563,"SEI":0.053833347841225634,"SEIadj":0.053833347841225634,"combinedScoreRank":155,"SEIrank":154,"engagementSEIrank":34,"voiceSEIrank":28,"audienceSEIrank":154},"non_scoped":{"SEI":0.03148656689821518,"SEIrank":137,"SEIadj":0,"audienceSEI":0.3148656689821518,"audienceSEIadj":0,"audienceSEIrank":137,"audienceScore":0.05829846116660405,"combinedScore":0.002914923058330203,"combinedScoreRank":137,"engagementSEI":0,"engagementSEIadj":0,"engagementSEIrank":34,"engagementScore":0,"voiceSEI":0,"voiceSEIadj":0,"voiceSEIrank":28,"voiceScore":0},"scoped":{"SEI":0.4133400865737574,"SEIrank":124,"SEIadj":0,"audienceSEI":4.133400865737574,"audienceSEIadj":0,"audienceSEIrank":124,"audienceScore":0.1684486488039316,"combinedScore":0.02406409268627594,"combinedScoreRank":124,"engagementSEI":0,"engagementSEIadj":0,"engagementSEIrank":27,"engagementScore":0,"voiceSEI":0,"voiceSEIadj":0,"voiceSEIrank":24,"voiceScore":0}},"facebook":{"entityString":"536575feb08f37d80186a099","type":"facebook","profiles":1,"postsMade":0,"repliesMade":0,"repliesRcvd":0,"sharesMade":0,"sharesRcvd":0,"mentionsRcvd":0,"likesRcvd":0,"reachRcvd":0,"audience":2302,"voice":0,"conversation":0,"engagement":0,"group_scoped":{"audienceScore":0.14962285550864945,"voiceScore":0,"engagementScore":0,"combinedScore":0.14962285550864945,"engagementSEI":0,"engagementSEIadj":0,"voiceSEI":0,"voiceSEIadj":0,"audienceSEI":0.21062069975113454,"audienceSEIadj":0.21062069975113454,"SEI":0.021062069975113454,"SEIadj":0.021062069975113454,"combinedScoreRank":141,"SEIrank":140,"engagementSEIrank":32,"voiceSEIrank":28,"audienceSEIrank":140},"non_scoped":{"SEI":0.012510216858250876,"SEIrank":139,"SEIadj":0,"audienceSEI":0.12510216858250875,"audienceSEIadj":0,"audienceSEIrank":139,"audienceScore":0.024003795561070473,"combinedScore":0.0012001897780535237,"combinedScoreRank":139,"engagementSEI":0,"engagementSEIadj":0,"engagementSEIrank":32,"engagementScore":0,"voiceSEI":0,"voiceSEIadj":0,"voiceSEIrank":28,"voiceScore":0},"scoped":{"SEI":0.16165616814488662,"SEIrank":124,"SEIadj":0,"audienceSEI":1.6165616814488661,"audienceSEIadj":0,"audienceSEIrank":124,"audienceScore":0.09895384890495229,"combinedScore":0.014136264129278897,"combinedScoreRank":124,"engagementSEI":0,"engagementSEIadj":0,"engagementSEIrank":25,"engagementScore":0,"voiceSEI":0,"voiceSEIadj":0,"voiceSEIrank":24,"voiceScore":0}},"twitter":{"entityString":"536575feb08f37d80186a099","type":"twitter","profiles":1,"postsMade":0,"repliesMade":0,"repliesRcvd":0,"sharesMade":0,"sharesRcvd":0,"mentionsRcvd":0,"likesRcvd":0,"reachRcvd":0,"audience":5614,"voice":0,"conversation":0,"engagement":0,"group_scoped":{"audienceScore":0.8929551343329638,"voiceScore":0,"engagementScore":0,"combinedScore":0.8929551343329638,"engagementSEI":0,"engagementSEIadj":0,"voiceSEI":0,"voiceSEIadj":0,"audienceSEI":2.1044503088826247,"audienceSEIadj":2.1044503088826247,"SEI":0.2104450308882625,"SEIadj":0.2104450308882625,"combinedScoreRank":149,"SEIrank":163,"engagementSEIrank":29,"voiceSEIrank":27,"audienceSEIrank":163},"non_scoped":{"SEI":0.1013225717957233,"SEIrank":119,"SEIadj":0,"audienceSEI":1.013225717957233,"audienceSEIadj":0,"audienceSEIrank":119,"audienceScore":0.16397780837554482,"combinedScore":0.00819889041877724,"combinedScoreRank":119,"engagementSEI":0,"engagementSEIadj":0,"engagementSEIrank":29,"engagementScore":0,"voiceSEI":0,"voiceSEIadj":0,"voiceSEIrank":27,"voiceScore":0},"scoped":{"SEI":0.48162796084520815,"SEIrank":105,"SEIadj":0,"audienceSEI":4.816279608452081,"audienceSEIadj":0,"audienceSEIrank":105,"audienceScore":0.2603210285972898,"combinedScore":0.037188718371041395,"combinedScoreRank":105,"engagementSEI":0,"engagementSEIadj":0,"engagementSEIrank":25,"engagementScore":0,"voiceSEI":0,"voiceSEIadj":0,"voiceSEIrank":24,"voiceScore":0}},"instagram":{"entityString":"536575feb08f37d80186a099","type":"instagram","profiles":0,"postsMade":0,"repliesMade":0,"repliesRcvd":0,"sharesMade":0,"sharesRcvd":0,"mentionsRcvd":0,"likesRcvd":0,"reachRcvd":0,"audience":0,"voice":0,"conversation":0,"engagement":0,"group_scoped":{"audienceScore":0,"voiceScore":0,"engagementScore":0,"combinedScore":0,"engagementSEI":0,"engagementSEIadj":0,"voiceSEI":0,"voiceSEIadj":0,"audienceSEI":0,"audienceSEIadj":0,"SEI":0,"SEIadj":0,"combinedScoreRank":71,"SEIrank":53,"engagementSEIrank":29,"voiceSEIrank":26,"audienceSEIrank":53},"non_scoped":{"SEI":0,"SEIrank":53,"SEIadj":0,"audienceSEI":0,"audienceSEIadj":0,"audienceSEIrank":53,"audienceScore":0,"combinedScore":0,"combinedScoreRank":53,"engagementSEI":0,"engagementSEIadj":0,"engagementSEIrank":29,"engagementScore":0,"voiceSEI":0,"voiceSEIadj":0,"voiceSEIrank":26,"voiceScore":0},"scoped":{"SEI":0,"SEIrank":46,"SEIadj":0,"audienceSEI":0,"audienceSEIadj":0,"audienceSEIrank":46,"audienceScore":0,"combinedScore":0,"combinedScoreRank":46,"engagementSEI":0,"engagementSEIadj":0,"engagementSEIrank":25,"engagementScore":0,"voiceSEI":0,"voiceSEIadj":0,"voiceSEIrank":24,"voiceScore":0}}},"hour":{"boundaryQuantum":4984410,"combined":{"entityString":"536575feb08f37d80186a099","type":"combined","profiles":2,"postsMade":0,"repliesMade":0,"repliesRcvd":0,"sharesMade":0,"sharesRcvd":0,"mentionsRcvd":0,"likesRcvd":0,"reachRcvd":0,"audience":7916,"voice":0,"conversation":0,"engagement":0,"group_scoped":{"audienceScore":0.34750238150634116,"voiceScore":0,"engagementScore":0,"combinedScore":0.34750238150634116,"combinedScoreRank":141,"SEIrank":159,"engagementSEIrank":77,"voiceSEIrank":38,"audienceSEIrank":154,"engagementSEI":0,"engagementSEIadj":0,"voiceSEI":0,"voiceSEIadj":0,"audienceSEI":0.5383334784122563,"audienceSEIadj":0.5383334784122563,"SEI":0.053833347841225634,"SEIadj":0.053833347841225634},"non_scoped":{"SEI":0.03148656689821518,"SEIrank":142,"SEIadj":0,"audienceSEI":0.3148656689821518,"audienceSEIadj":0,"audienceSEIrank":137,"audienceScore":0.05829846116660405,"combinedScore":0.002914923058330203,"combinedScoreRank":144,"engagementSEI":0,"engagementSEIadj":0,"engagementSEIrank":77,"engagementScore":0,"voiceSEI":0,"voiceSEIadj":0,"voiceSEIrank":38,"voiceScore":0},"scoped":{"SEI":0.4133400865737574,"SEIrank":127,"SEIadj":0,"audienceSEI":4.133400865737574,"audienceSEIadj":0,"audienceSEIrank":124,"audienceScore":0.1684486488039316,"combinedScore":0.00842243244019658,"combinedScoreRank":131,"engagementSEI":0,"engagementSEIadj":0,"engagementSEIrank":67,"engagementScore":0,"voiceSEI":0,"voiceSEIadj":0,"voiceSEIrank":31,"voiceScore":0}},"facebook":{"entityString":"536575feb08f37d80186a099","type":"facebook","profiles":1,"postsMade":0,"repliesMade":0,"repliesRcvd":0,"sharesMade":0,"sharesRcvd":0,"mentionsRcvd":0,"likesRcvd":0,"reachRcvd":0,"audience":2302,"voice":0,"conversation":0,"engagement":0,"group_scoped":{"audienceScore":0.14962285550864945,"voiceScore":0,"engagementScore":0,"combinedScore":0.14962285550864945,"combinedScoreRank":138,"SEIrank":142,"engagementSEIrank":63,"voiceSEIrank":32,"audienceSEIrank":140,"engagementSEI":0,"engagementSEIadj":0,"voiceSEI":0,"voiceSEIadj":0,"audienceSEI":0.21062069975113454,"audienceSEIadj":0.21062069975113454,"SEI":0.021062069975113454,"SEIadj":0.021062069975113454},"non_scoped":{"SEI":0.012510216858250876,"SEIrank":139,"SEIadj":0,"audienceSEI":0.12510216858250875,"audienceSEIadj":0,"audienceSEIrank":139,"audienceScore":0.024003795561070473,"combinedScore":0.0012001897780535237,"combinedScoreRank":140,"engagementSEI":0,"engagementSEIadj":0,"engagementSEIrank":63,"engagementScore":0,"voiceSEI":0,"voiceSEIadj":0,"voiceSEIrank":32,"voiceScore":0},"scoped":{"SEI":0.16165616814488662,"SEIrank":125,"SEIadj":0,"audienceSEI":1.6165616814488661,"audienceSEIadj":0,"audienceSEIrank":124,"audienceScore":0.09895384890495229,"combinedScore":0.004947692445247615,"combinedScoreRank":125,"engagementSEI":0,"engagementSEIadj":0,"engagementSEIrank":53,"engagementScore":0,"voiceSEI":0,"voiceSEIadj":0,"voiceSEIrank":25,"voiceScore":0}},"twitter":{"entityString":"536575feb08f37d80186a099","type":"twitter","profiles":1,"postsMade":0,"repliesMade":0,"repliesRcvd":0,"sharesMade":0,"sharesRcvd":0,"mentionsRcvd":0,"likesRcvd":0,"reachRcvd":0,"audience":5614,"voice":0,"conversation":0,"engagement":0,"group_scoped":{"audienceScore":0.8929551343329638,"voiceScore":0,"engagementScore":0,"combinedScore":0.8929551343329638,"combinedScoreRank":154,"SEIrank":167,"engagementSEIrank":57,"voiceSEIrank":36,"audienceSEIrank":163,"engagementSEI":0,"engagementSEIadj":0,"voiceSEI":0,"voiceSEIadj":0,"audienceSEI":2.1044503088826247,"audienceSEIadj":2.1044503088826247,"SEI":0.2104450308882625,"SEIadj":0.2104450308882625},"non_scoped":{"SEI":0.1013225717957233,"SEIrank":127,"SEIadj":0,"audienceSEI":1.013225717957233,"audienceSEIadj":0,"audienceSEIrank":119,"audienceScore":0.16397780837554482,"combinedScore":0.00819889041877724,"combinedScoreRank":127,"engagementSEI":0,"engagementSEIadj":0,"engagementSEIrank":57,"engagementScore":0,"voiceSEI":0,"voiceSEIadj":0,"voiceSEIrank":36,"voiceScore":0},"scoped":{"SEI":0.48162796084520815,"SEIrank":113,"SEIadj":0,"audienceSEI":4.816279608452081,"audienceSEIadj":0,"audienceSEIrank":105,"audienceScore":0.2603210285972898,"combinedScore":0.01301605142986449,"combinedScoreRank":113,"engagementSEI":0,"engagementSEIadj":0,"engagementSEIrank":50,"engagementScore":0,"voiceSEI":0,"voiceSEIadj":0,"voiceSEIrank":31,"voiceScore":0}},"instagram":{"entityString":"536575feb08f37d80186a099","type":"instagram","profiles":0,"postsMade":0,"repliesMade":0,"repliesRcvd":0,"sharesMade":0,"sharesRcvd":0,"mentionsRcvd":0,"likesRcvd":0,"reachRcvd":0,"audience":0,"voice":0,"conversation":0,"engagement":0,"group_scoped":{"audienceScore":0,"voiceScore":0,"engagementScore":0,"combinedScore":0,"combinedScoreRank":71,"SEIrank":53,"engagementSEIrank":35,"voiceSEIrank":26,"audienceSEIrank":53,"engagementSEI":0,"engagementSEIadj":0,"voiceSEI":0,"voiceSEIadj":0,"audienceSEI":0,"audienceSEIadj":0,"SEI":0,"SEIadj":0},"non_scoped":{"SEI":0,"SEIrank":53,"SEIadj":0,"audienceSEI":0,"audienceSEIadj":0,"audienceSEIrank":53,"audienceScore":0,"combinedScore":0,"combinedScoreRank":53,"engagementSEI":0,"engagementSEIadj":0,"engagementSEIrank":35,"engagementScore":0,"voiceSEI":0,"voiceSEIadj":0,"voiceSEIrank":26,"voiceScore":0},"scoped":{"SEI":0,"SEIrank":46,"SEIadj":0,"audienceSEI":0,"audienceSEIadj":0,"audienceSEIrank":46,"audienceScore":0,"combinedScore":0,"combinedScoreRank":46,"engagementSEI":0,"engagementSEIadj":0,"engagementSEIrank":30,"engagementScore":0,"voiceSEI":0,"voiceSEIadj":0,"voiceSEIrank":24,"voiceScore":0}}},"today":{"boundaryQuantum":4984134,"combined":{"entityString":"536575feb08f37d80186a099","type":"combined","profiles":2,"postsMade":0,"repliesMade":0,"repliesRcvd":0,"sharesMade":0,"sharesRcvd":0,"mentionsRcvd":0,"likesRcvd":0,"reachRcvd":0,"audience":7916,"voice":0,"conversation":0,"engagement":0,"group_scoped":{"audienceScore":0.34750238150634116,"voiceScore":0,"engagementScore":0,"combinedScore":0.34750238150634116,"combinedScoreRank":96,"SEIrank":181,"engagementSEIrank":171,"voiceSEIrank":124,"audienceSEIrank":154,"engagementSEI":0,"engagementSEIadj":0,"voiceSEI":0,"voiceSEIadj":0,"audienceSEI":0.5383334784122563,"audienceSEIadj":0.5383334784122563,"SEI":0.053833347841225634,"SEIadj":0.053833347841225634},"non_scoped":{"SEI":0.03148656689821518,"SEIrank":164,"SEIadj":0,"audienceSEI":0.3148656689821518,"audienceSEIadj":0,"audienceSEIrank":137,"audienceScore":0.05829846116660405,"combinedScore":0.002914923058330203,"combinedScoreRank":171,"engagementSEI":0,"engagementSEIadj":0,"engagementSEIrank":171,"engagementScore":0,"voiceSEI":0,"voiceSEIadj":0,"voiceSEIrank":124,"voiceScore":0},"scoped":{"SEI":0.4133400865737574,"SEIrank":149,"SEIadj":0,"audienceSEI":4.133400865737574,"audienceSEIadj":0,"audienceSEIrank":124,"audienceScore":0.1684486488039316,"combinedScore":0.00842243244019658,"combinedScoreRank":162,"engagementSEI":0,"engagementSEIadj":0,"engagementSEIrank":158,"engagementScore":0,"voiceSEI":0,"voiceSEIadj":0,"voiceSEIrank":112,"voiceScore":0}},"facebook":{"entityString":"536575feb08f37d80186a099","type":"facebook","profiles":1,"postsMade":0,"repliesMade":0,"repliesRcvd":0,"sharesMade":0,"sharesRcvd":0,"mentionsRcvd":0,"likesRcvd":0,"reachRcvd":0,"audience":2302,"voice":0,"conversation":0,"engagement":0,"group_scoped":{"audienceScore":0.14962285550864945,"voiceScore":0,"engagementScore":0,"combinedScore":0.14962285550864945,"combinedScoreRank":117,"SEIrank":144,"engagementSEIrank":125,"voiceSEIrank":75,"audienceSEIrank":140,"engagementSEI":0,"engagementSEIadj":0,"voiceSEI":0,"voiceSEIadj":0,"audienceSEI":0.21062069975113454,"audienceSEIadj":0.21062069975113454,"SEI":0.021062069975113454,"SEIadj":0.021062069975113454},"non_scoped":{"SEI":0.012510216858250876,"SEIrank":144,"SEIadj":0,"audienceSEI":0.12510216858250875,"audienceSEIadj":0,"audienceSEIrank":139,"audienceScore":0.024003795561070473,"combinedScore":0.0012001897780535237,"combinedScoreRank":147,"engagementSEI":0,"engagementSEIadj":0,"engagementSEIrank":125,"engagementScore":0,"voiceSEI":0,"voiceSEIadj":0,"voiceSEIrank":75,"voiceScore":0},"scoped":{"SEI":0.16165616814488662,"SEIrank":131,"SEIadj":0,"audienceSEI":1.6165616814488661,"audienceSEIadj":0,"audienceSEIrank":124,"audienceScore":0.09895384890495229,"combinedScore":0.004947692445247615,"combinedScoreRank":134,"engagementSEI":0,"engagementSEIadj":0,"engagementSEIrank":114,"engagementScore":0,"voiceSEI":0,"voiceSEIadj":0,"voiceSEIrank":66,"voiceScore":0}},"twitter":{"entityString":"536575feb08f37d80186a099","type":"twitter","profiles":1,"postsMade":0,"repliesMade":0,"repliesRcvd":0,"sharesMade":0,"sharesRcvd":0,"mentionsRcvd":0,"likesRcvd":0,"reachRcvd":0,"audience":5614,"voice":0,"conversation":0,"engagement":0,"group_scoped":{"audienceScore":0.8929551343329638,"voiceScore":0,"engagementScore":0,"combinedScore":0.8929551343329638,"combinedScoreRank":142,"SEIrank":188,"engagementSEIrank":143,"voiceSEIrank":112,"audienceSEIrank":163,"engagementSEI":0,"engagementSEIadj":0,"voiceSEI":0,"voiceSEIadj":0,"audienceSEI":2.1044503088826247,"audienceSEIadj":2.1044503088826247,"SEI":0.2104450308882625,"SEIadj":0.2104450308882625},"non_scoped":{"SEI":0.1013225717957233,"SEIrank":166,"SEIadj":0,"audienceSEI":1.013225717957233,"audienceSEIadj":0,"audienceSEIrank":119,"audienceScore":0.16397780837554482,"combinedScore":0.00819889041877724,"combinedScoreRank":171,"engagementSEI":0,"engagementSEIadj":0,"engagementSEIrank":143,"engagementScore":0,"voiceSEI":0,"voiceSEIadj":0,"voiceSEIrank":112,"voiceScore":0},"scoped":{"SEI":0.48162796084520815,"SEIrank":145,"SEIadj":0,"audienceSEI":4.816279608452081,"audienceSEIadj":0,"audienceSEIrank":105,"audienceScore":0.2603210285972898,"combinedScore":0.01301605142986449,"combinedScoreRank":155,"engagementSEI":0,"engagementSEIadj":0,"engagementSEIrank":131,"engagementScore":0,"voiceSEI":0,"voiceSEIadj":0,"voiceSEIrank":100,"voiceScore":0}},"instagram":{"entityString":"536575feb08f37d80186a099","type":"instagram","profiles":0,"postsMade":0,"repliesMade":0,"repliesRcvd":0,"sharesMade":0,"sharesRcvd":0,"mentionsRcvd":0,"likesRcvd":0,"reachRcvd":0,"audience":0,"voice":0,"conversation":0,"engagement":0,"group_scoped":{"audienceScore":0,"voiceScore":0,"engagementScore":0,"combinedScore":0,"combinedScoreRank":71,"SEIrank":53,"engagementSEIrank":45,"voiceSEIrank":32,"audienceSEIrank":53,"engagementSEI":0,"engagementSEIadj":0,"voiceSEI":0,"voiceSEIadj":0,"audienceSEI":0,"audienceSEIadj":0,"SEI":0,"SEIadj":0},"non_scoped":{"SEI":0,"SEIrank":53,"SEIadj":0,"audienceSEI":0,"audienceSEIadj":0,"audienceSEIrank":53,"audienceScore":0,"combinedScore":0,"combinedScoreRank":53,"engagementSEI":0,"engagementSEIadj":0,"engagementSEIrank":45,"engagementScore":0,"voiceSEI":0,"voiceSEIadj":0,"voiceSEIrank":32,"voiceScore":0},"scoped":{"SEI":0,"SEIrank":46,"SEIadj":0,"audienceSEI":0,"audienceSEIadj":0,"audienceSEIrank":46,"audienceScore":0,"combinedScore":0,"combinedScoreRank":46,"engagementSEI":0,"engagementSEIadj":0,"engagementSEIrank":38,"engagementScore":0,"voiceSEI":0,"voiceSEIadj":0,"voiceSEIrank":26,"voiceScore":0}}},"week":{"boundaryQuantum":4982406,"combined":{"entityString":"536575feb08f37d80186a099","type":"combined","profiles":2,"postsMade":0,"repliesMade":0,"repliesRcvd":0,"sharesMade":0,"sharesRcvd":0,"mentionsRcvd":0,"likesRcvd":0,"reachRcvd":0,"audience":7916,"voice":0,"conversation":0,"engagement":0,"group_scoped":{"audienceScore":0.34750238150634116,"voiceScore":0,"engagementScore":0,"combinedScore":0.34750238150634116,"combinedScoreRank":78,"SEIrank":213,"engagementSEIrank":203,"voiceSEIrank":205,"audienceSEIrank":154,"engagementSEI":0,"engagementSEIadj":0,"voiceSEI":0,"voiceSEIadj":0,"audienceSEI":0.5383334784122563,"audienceSEIadj":0.5383334784122563,"SEI":0.053833347841225634,"SEIadj":0.053833347841225634},"non_scoped":{"SEI":0.03148656689821518,"SEIrank":208,"SEIadj":0,"audienceSEI":0.3148656689821518,"audienceSEIadj":0,"audienceSEIrank":137,"audienceScore":0.05829846116660405,"combinedScore":0.002914923058330203,"combinedScoreRank":199,"engagementSEI":0,"engagementSEIadj":0,"engagementSEIrank":203,"engagementScore":0,"voiceSEI":0,"voiceSEIadj":0,"voiceSEIrank":205,"voiceScore":0},"scoped":{"SEI":0.4133400865737574,"SEIrank":186,"SEIadj":0,"audienceSEI":4.133400865737574,"audienceSEIadj":0,"audienceSEIrank":124,"audienceScore":0.1684486488039316,"combinedScore":0.00842243244019658,"combinedScoreRank":182,"engagementSEI":0,"engagementSEIadj":0,"engagementSEIrank":187,"engagementScore":0,"voiceSEI":0,"voiceSEIadj":0,"voiceSEIrank":189,"voiceScore":0}},"facebook":{"entityString":"536575feb08f37d80186a099","type":"facebook","profiles":1,"postsMade":0,"repliesMade":0,"repliesRcvd":0,"sharesMade":0,"sharesRcvd":0,"mentionsRcvd":0,"likesRcvd":0,"reachRcvd":0,"audience":2302,"voice":0,"conversation":0,"engagement":0,"group_scoped":{"audienceScore":0.14962285550864945,"voiceScore":0,"engagementScore":0,"combinedScore":0.14962285550864945,"combinedScoreRank":104,"SEIrank":155,"engagementSEIrank":145,"voiceSEIrank":141,"audienceSEIrank":140,"engagementSEI":0,"engagementSEIadj":0,"voiceSEI":0,"voiceSEIadj":0,"audienceSEI":0.21062069975113454,"audienceSEIadj":0.21062069975113454,"SEI":0.021062069975113454,"SEIadj":0.021062069975113454},"non_scoped":{"SEI":0.012510216858250876,"SEIrank":155,"SEIadj":0,"audienceSEI":0.12510216858250875,"audienceSEIadj":0,"audienceSEIrank":139,"audienceScore":0.024003795561070473,"combinedScore":0.0012001897780535237,"combinedScoreRank":155,"engagementSEI":0,"engagementSEIadj":0,"engagementSEIrank":145,"engagementScore":0,"voiceSEI":0,"voiceSEIadj":0,"voiceSEIrank":141,"voiceScore":0},"scoped":{"SEI":0.16165616814488662,"SEIrank":140,"SEIadj":0,"audienceSEI":1.6165616814488661,"audienceSEIadj":0,"audienceSEIrank":124,"audienceScore":0.09895384890495229,"combinedScore":0.004947692445247615,"combinedScoreRank":141,"engagementSEI":0,"engagementSEIadj":0,"engagementSEIrank":134,"engagementScore":0,"voiceSEI":0,"voiceSEIadj":0,"voiceSEIrank":130,"voiceScore":0}},"twitter":{"entityString":"536575feb08f37d80186a099","type":"twitter","profiles":1,"postsMade":0,"repliesMade":0,"repliesRcvd":0,"sharesMade":0,"sharesRcvd":0,"mentionsRcvd":0,"likesRcvd":0,"reachRcvd":0,"audience":5614,"voice":0,"conversation":0,"engagement":0,"group_scoped":{"audienceScore":0.8929551343329638,"voiceScore":0,"engagementScore":0,"combinedScore":0.8929551343329638,"combinedScoreRank":109,"SEIrank":204,"engagementSEIrank":193,"voiceSEIrank":195,"audienceSEIrank":163,"engagementSEI":0,"engagementSEIadj":0,"voiceSEI":0,"voiceSEIadj":0,"audienceSEI":2.1044503088826247,"audienceSEIadj":2.1044503088826247,"SEI":0.2104450308882625,"SEIadj":0.2104450308882625},"non_scoped":{"SEI":0.1013225717957233,"SEIrank":194,"SEIadj":0,"audienceSEI":1.013225717957233,"audienceSEIadj":0,"audienceSEIrank":119,"audienceScore":0.16397780837554482,"combinedScore":0.00819889041877724,"combinedScoreRank":188,"engagementSEI":0,"engagementSEIadj":0,"engagementSEIrank":193,"engagementScore":0,"voiceSEI":0,"voiceSEIadj":0,"voiceSEIrank":195,"voiceScore":0},"scoped":{"SEI":0.48162796084520815,"SEIrank":174,"SEIadj":0,"audienceSEI":4.816279608452081,"audienceSEIadj":0,"audienceSEIrank":105,"audienceScore":0.2603210285972898,"combinedScore":0.01301605142986449,"combinedScoreRank":172,"engagementSEI":0,"engagementSEIadj":0,"engagementSEIrank":178,"engagementScore":0,"voiceSEI":0,"voiceSEIadj":0,"voiceSEIrank":180,"voiceScore":0}},"instagram":{"entityString":"536575feb08f37d80186a099","type":"instagram","profiles":0,"postsMade":0,"repliesMade":0,"repliesRcvd":0,"sharesMade":0,"sharesRcvd":0,"mentionsRcvd":0,"likesRcvd":0,"reachRcvd":0,"audience":0,"voice":0,"conversation":0,"engagement":0,"group_scoped":{"audienceScore":0,"voiceScore":0,"engagementScore":0,"combinedScore":0,"combinedScoreRank":71,"SEIrank":53,"engagementSEIrank":48,"voiceSEIrank":46,"audienceSEIrank":53,"engagementSEI":0,"engagementSEIadj":0,"voiceSEI":0,"voiceSEIadj":0,"audienceSEI":0,"audienceSEIadj":0,"SEI":0,"SEIadj":0},"non_scoped":{"SEI":0,"SEIrank":53,"SEIadj":0,"audienceSEI":0,"audienceSEIadj":0,"audienceSEIrank":53,"audienceScore":0,"combinedScore":0,"combinedScoreRank":53,"engagementSEI":0,"engagementSEIadj":0,"engagementSEIrank":48,"engagementScore":0,"voiceSEI":0,"voiceSEIadj":0,"voiceSEIrank":46,"voiceScore":0},"scoped":{"SEI":0,"SEIrank":46,"SEIadj":0,"audienceSEI":0,"audienceSEIadj":0,"audienceSEIrank":46,"audienceScore":0,"combinedScore":0,"combinedScoreRank":46,"engagementSEI":0,"engagementSEIadj":0,"engagementSEIrank":41,"engagementScore":0,"voiceSEI":0,"voiceSEIadj":0,"voiceSEIrank":39,"voiceScore":0}}},"month":{"boundaryQuantum":4975782,"combined":{"entityString":"536575feb08f37d80186a099","type":"combined","profiles":2,"postsMade":8,"repliesMade":0,"repliesRcvd":0,"sharesMade":0,"sharesRcvd":19,"mentionsRcvd":0,"likesRcvd":40,"reachRcvd":0,"audience":7916,"voice":8,"conversation":8,"engagement":59,"group_scoped":{"audienceScore":0.34750238150634116,"voiceScore":0.11212333566923616,"engagementScore":0.00956074068192388,"combinedScore":0.031585952472510365,"combinedScoreRank":211,"SEIrank":200,"engagementSEIrank":180,"voiceSEIrank":192,"audienceSEIrank":154,"engagementSEI":0.010905972036348311,"engagementSEIadj":0.010905972036348311,"voiceSEI":0.26490066225165565,"voiceSEIadj":0.26490066225165565,"audienceSEI":0.5383334784122563,"audienceSEIadj":0.5383334784122563,"SEI":0.1398471297385313,"SEIadj":0.1398471297385313},"non_scoped":{"SEI":0.0987800927411468,"SEIrank":194,"SEIadj":0,"audienceSEI":0.3148656689821518,"audienceSEIadj":0,"audienceSEIrank":137,"audienceScore":0.05829846116660405,"combinedScore":0.004551212386079277,"combinedScoreRank":192,"engagementSEI":0.0016281063026478528,"engagementSEIadj":0,"engagementSEIrank":188,"engagementScore":0.0006412306063063617,"voiceSEI":0.22105554020447638,"voiceSEIadj":0,"voiceSEIrank":188,"voiceScore":0.021183635641466966},"scoped":{"SEI":0.698718515718162,"SEIrank":176,"SEIadj":0,"audienceSEI":4.133400865737574,"audienceSEIadj":0,"audienceSEIrank":124,"audienceScore":0.1684486488039316,"combinedScore":0.016252718545249227,"combinedScoreRank":174,"engagementSEI":0.05457808366172689,"engagementSEIadj":0,"engagementSEIrank":174,"engagementScore":0.006218774374433459,"voiceSEI":0.8421052631578947,"voiceSEIadj":0,"voiceSEIrank":176,"voiceScore":0.0446677833612507}},"facebook":{"entityString":"536575feb08f37d80186a099","type":"facebook","profiles":1,"postsMade":0,"repliesMade":0,"repliesRcvd":0,"sharesMade":0,"sharesRcvd":0,"mentionsRcvd":0,"likesRcvd":0,"reachRcvd":0,"audience":2302,"voice":0,"conversation":0,"engagement":0,"group_scoped":{"audienceScore":0.14962285550864945,"voiceScore":0,"engagementScore":0,"combinedScore":0.14962285550864945,"combinedScoreRank":101,"SEIrank":158,"engagementSEIrank":156,"voiceSEIrank":154,"audienceSEIrank":140,"engagementSEI":0,"engagementSEIadj":0,"voiceSEI":0,"voiceSEIadj":0,"audienceSEI":0.21062069975113454,"audienceSEIadj":0.21062069975113454,"SEI":0.021062069975113454,"SEIadj":0.021062069975113454},"non_scoped":{"SEI":0.012510216858250876,"SEIrank":157,"SEIadj":0,"audienceSEI":0.12510216858250875,"audienceSEIadj":0,"audienceSEIrank":139,"audienceScore":0.024003795561070473,"combinedScore":0.0012001897780535237,"combinedScoreRank":157,"engagementSEI":0,"engagementSEIadj":0,"engagementSEIrank":156,"engagementScore":0,"voiceSEI":0,"voiceSEIadj":0,"voiceSEIrank":154,"voiceScore":0},"scoped":{"SEI":0.16165616814488662,"SEIrank":142,"SEIadj":0,"audienceSEI":1.6165616814488661,"audienceSEIadj":0,"audienceSEIrank":124,"audienceScore":0.09895384890495229,"combinedScore":0.004947692445247615,"combinedScoreRank":142,"engagementSEI":0,"engagementSEIadj":0,"engagementSEIrank":144,"engagementScore":0,"voiceSEI":0,"voiceSEIadj":0,"voiceSEIrank":143,"voiceScore":0}},"twitter":{"entityString":"536575feb08f37d80186a099","type":"twitter","profiles":1,"postsMade":8,"repliesMade":0,"repliesRcvd":0,"sharesMade":0,"sharesRcvd":19,"mentionsRcvd":0,"likesRcvd":40,"reachRcvd":0,"audience":5614,"voice":8,"conversation":8,"engagement":59,"group_scoped":{"audienceScore":0.8929551343329638,"voiceScore":0.1616161616161616,"engagementScore":0.11119696941140993,"combinedScore":0.1528058372677252,"combinedScoreRank":197,"SEIrank":194,"engagementSEIrank":183,"voiceSEIrank":184,"audienceSEIrank":163,"engagementSEI":0.19698841441020332,"engagementSEIadj":0.19698841441020332,"voiceSEI":0.4028197381671702,"voiceSEIadj":0.4028197381671702,"audienceSEI":2.1044503088826247,"audienceSEIadj":2.1044503088826247,"SEI":0.44948400098453556,"SEIadj":0.44948400098453556},"non_scoped":{"SEI":0.2832276424975614,"SEIrank":172,"SEIadj":0,"audienceSEI":1.013225717957233,"audienceSEIadj":0,"audienceSEIrank":119,"audienceScore":0.16397780837554482,"combinedScore":0.031924580993462494,"combinedScoreRank":160,"engagementSEI":0.10237190498499124,"engagementSEIadj":0,"engagementSEIrank":162,"engagementScore":0.02445504623661708,"voiceSEI":0.4016064257028112,"voiceSEIadj":0,"voiceSEIrank":172,"voiceScore":0.03432297923459756},"scoped":{"SEI":1.2035145126016724,"SEIrank":158,"SEIadj":0,"audienceSEI":4.816279608452081,"audienceSEIadj":0,"audienceSEIrank":105,"audienceScore":0.2603210285972898,"combinedScore":0.060819912364806245,"combinedScoreRank":149,"engagementSEI":0.5820262405050804,"engagementSEIadj":0,"engagementSEIrank":150,"engagementScore":0.04964073569253034,"voiceSEI":1.2422360248447204,"voiceSEIadj":0,"voiceSEIrank":160,"voiceScore":0.06254397623328903}},"instagram":{"entityString":"536575feb08f37d80186a099","type":"instagram","profiles":0,"postsMade":0,"repliesMade":0,"repliesRcvd":0,"sharesMade":0,"sharesRcvd":0,"mentionsRcvd":0,"likesRcvd":0,"reachRcvd":0,"audience":0,"voice":0,"conversation":0,"engagement":0,"group_scoped":{"audienceScore":0,"voiceScore":0,"engagementScore":0,"combinedScore":0,"combinedScoreRank":71,"SEIrank":53,"engagementSEIrank":48,"voiceSEIrank":47,"audienceSEIrank":53,"engagementSEI":0,"engagementSEIadj":0,"voiceSEI":0,"voiceSEIadj":0,"audienceSEI":0,"audienceSEIadj":0,"SEI":0,"SEIadj":0},"non_scoped":{"SEI":0,"SEIrank":53,"SEIadj":0,"audienceSEI":0,"audienceSEIadj":0,"audienceSEIrank":53,"audienceScore":0,"combinedScore":0,"combinedScoreRank":53,"engagementSEI":0,"engagementSEIadj":0,"engagementSEIrank":48,"engagementScore":0,"voiceSEI":0,"voiceSEIadj":0,"voiceSEIrank":47,"voiceScore":0},"scoped":{"SEI":0,"SEIrank":46,"SEIadj":0,"audienceSEI":0,"audienceSEIadj":0,"audienceSEIrank":46,"audienceScore":0,"combinedScore":0,"combinedScoreRank":46,"engagementSEI":0,"engagementSEIadj":0,"engagementSEIrank":41,"engagementScore":0,"voiceSEI":0,"voiceSEIadj":0,"voiceSEIrank":40,"voiceScore":0}}},"quarter":{"boundaryQuantum":4958502,"combined":{"entityString":"536575feb08f37d80186a099","type":"combined","profiles":2,"postsMade":26,"repliesMade":0,"repliesRcvd":1,"sharesMade":0,"sharesRcvd":46,"mentionsRcvd":0,"likesRcvd":141,"reachRcvd":0,"audience":7916,"voice":26,"conversation":27,"engagement":188,"group_scoped":{"audienceScore":0.34750238150634116,"voiceScore":0.12850294074037463,"engagementScore":0.0089976003208506,"combinedScore":0.03189810640110133,"combinedScoreRank":212,"SEIrank":200,"engagementSEIrank":186,"voiceSEIrank":192,"audienceSEIrank":154,"engagementSEI":0.010039844296967913,"engagementSEIadj":0.010039844296967913,"voiceSEI":0.2815681178254278,"voiceSEIadj":0.2815681178254278,"audienceSEI":0.5383334784122563,"audienceSEIadj":0.5383334784122563,"SEI":0.14432768976703472,"SEIadj":0.14432768976703472},"non_scoped":{"SEI":0.10531327526267956,"SEIrank":195,"SEIadj":0,"audienceSEI":0.3148656689821518,"audienceSEIadj":0,"audienceSEIrank":137,"audienceScore":0.05829846116660405,"combinedScore":0.004642922162427896,"combinedScoreRank":189,"engagementSEI":0.0016399566004676666,"engagementSEIadj":0,"engagementSEIrank":190,"engagementScore":0.0006351347059900635,"voiceSEI":0.24280911468061261,"voiceSEIadj":0,"voiceSEIrank":191,"voiceScore":0.023127557374132718},"scoped":{"SEI":0.7397859094430568,"SEIrank":178,"SEIadj":0,"audienceSEI":4.133400865737574,"audienceSEIadj":0,"audienceSEIrank":124,"audienceScore":0.1684486488039316,"combinedScore":0.016439267932959797,"combinedScoreRank":177,"engagementSEI":0.03804289538810836,"engagementSEIadj":0,"engagementSEIrank":177,"engagementScore":0.006205476531085806,"voiceSEI":1.012066952121448,"voiceSEIadj":0,"voiceSEIrank":179,"voiceScore":0.048638132295719845}},"facebook":{"entityString":"536575feb08f37d80186a099","type":"facebook","profiles":1,"postsMade":1,"repliesMade":0,"repliesRcvd":1,"sharesMade":0,"sharesRcvd":0,"mentionsRcvd":0,"likesRcvd":8,"reachRcvd":0,"audience":2302,"voice":1,"conversation":2,"engagement":9,"group_scoped":{"audienceScore":0.14962285550864945,"voiceScore":0.016257519102584946,"engagementScore":0.0005726648002036142,"combinedScore":0.008809417050744974,"combinedScoreRank":165,"SEIrank":155,"engagementSEIrank":149,"voiceSEIrank":150,"audienceSEIrank":140,"engagementSEI":0.000631565208055123,"engagementSEIadj":0.000631565208055123,"voiceSEI":0.0341646737273659,"voiceSEIadj":0.0341646737273659,"audienceSEI":0.21062069975113454,"audienceSEIadj":0.21062069975113454,"SEI":0.0316904112181563,"SEIadj":0.0316904112181563},"non_scoped":{"SEI":0.01885753484220756,"SEIrank":153,"SEIadj":0,"audienceSEI":0.12510216858250875,"audienceSEIadj":0,"audienceSEIrank":139,"audienceScore":0.024003795561070473,"combinedScore":0.001353808858073146,"combinedScoreRank":155,"engagementSEI":0.0000812777512722,"engagementSEIadj":0,"engagementSEIrank":150,"engagementScore":0.00003382455481530308,"voiceSEI":0.02099517111064455,"voiceSEIadj":0,"voiceSEIrank":150,"voiceScore":0.0024635396137169885},"scoped":{"SEI":0.20283344882702864,"SEIrank":140,"SEIadj":0,"audienceSEI":1.6165616814488661,"audienceSEIadj":0,"audienceSEIrank":124,"audienceScore":0.09895384890495229,"combinedScore":0.0056958393312932475,"combinedScoreRank":139,"engagementSEI":0.007653191380805797,"engagementSEIadj":0,"engagementSEIrank":138,"engagementScore":0.0004521072719947676,"voiceSEI":0.12195121951219512,"voiceSEIadj":0,"voiceSEIrank":139,"voiceScore":0.006825006825006826}},"twitter":{"entityString":"536575feb08f37d80186a099","type":"twitter","profiles":1,"postsMade":25,"repliesMade":0,"repliesRcvd":0,"sharesMade":0,"sharesRcvd":46,"mentionsRcvd":0,"likesRcvd":133,"reachRcvd":0,"audience":5614,"voice":25,"conversation":25,"engagement":179,"group_scoped":{"audienceScore":0.8929551343329638,"voiceScore":0.18143551781696785,"engagementScore":0.10079850435291864,"combinedScore":0.14443818652512336,"combinedScoreRank":193,"SEIrank":194,"engagementSEIrank":187,"voiceSEIrank":184,"audienceSEIrank":163,"engagementSEI":0.16690910447204504,"engagementSEIadj":0.16690910447204504,"voiceSEI":0.4163890739506996,"voiceSEIadj":0.4163890739506996,"audienceSEI":2.1044503088826247,"audienceSEIadj":2.1044503088826247,"SEI":0.4355072157566994,"SEIadj":0.4355072157566994},"non_scoped":{"SEI":0.2770874977447052,"SEIrank":177,"SEIadj":0,"audienceSEI":1.013225717957233,"audienceSEIadj":0,"audienceSEIrank":119,"audienceScore":0.16397780837554482,"combinedScore":0.02937822094780118,"combinedScoreRank":168,"engagementSEI":0.08488561781554688,"engagementSEIadj":0,"engagementSEIrank":167,"engagementScore":0.021537202810665124,"voiceSEI":0.41611185086551267,"voiceSEIadj":0,"voiceSEIrank":179,"voiceScore":0.035916959988506574},"scoped":{"SEI":1.2392103817010216,"SEIrank":162,"SEIadj":0,"audienceSEI":4.816279608452081,"audienceSEIadj":0,"audienceSEIrank":105,"audienceScore":0.2603210285972898,"combinedScore":0.05647769263651149,"combinedScoreRank":157,"engagementSEI":0.5631410054741082,"engagementSEIadj":0,"engagementSEIrank":155,"engagementScore":0.044651543346920036,"voiceSEI":1.3989927252378287,"voiceSEIadj":0,"voiceSEIrank":167,"voiceScore":0.0655050438883794}},"instagram":{"entityString":"536575feb08f37d80186a099","type":"instagram","profiles":0,"postsMade":0,"repliesMade":0,"repliesRcvd":0,"sharesMade":0,"sharesRcvd":0,"mentionsRcvd":0,"likesRcvd":0,"reachRcvd":0,"audience":0,"voice":0,"conversation":0,"engagement":0,"group_scoped":{"audienceScore":0,"voiceScore":0,"engagementScore":0,"combinedScore":0,"combinedScoreRank":71,"SEIrank":53,"engagementSEIrank":48,"voiceSEIrank":48,"audienceSEIrank":53,"engagementSEI":0,"engagementSEIadj":0,"voiceSEI":0,"voiceSEIadj":0,"audienceSEI":0,"audienceSEIadj":0,"SEI":0,"SEIadj":0},"non_scoped":{"SEI":0,"SEIrank":53,"SEIadj":0,"audienceSEI":0,"audienceSEIadj":0,"audienceSEIrank":53,"audienceScore":0,"combinedScore":0,"combinedScoreRank":53,"engagementSEI":0,"engagementSEIadj":0,"engagementSEIrank":48,"engagementScore":0,"voiceSEI":0,"voiceSEIadj":0,"voiceSEIrank":48,"voiceScore":0},"scoped":{"SEI":0,"SEIrank":46,"SEIadj":0,"audienceSEI":0,"audienceSEIadj":0,"audienceSEIrank":46,"audienceScore":0,"combinedScore":0,"combinedScoreRank":46,"engagementSEI":0,"engagementSEIadj":0,"engagementSEIrank":41,"engagementScore":0,"voiceSEI":0,"voiceSEIadj":0,"voiceSEIrank":41,"voiceScore":0}}},"blended":{"combined":{"non_scoped":{"SEI":0.0784939499568871,"SEIadj":40.047096369974135,"SEIrank":201,"audienceSEI":0.3148656689821518,"audienceSEIadj":50.157432834491075,"audienceSEIrank":137,"engagementSEI":0.0010641942456310113,"engagementSEIadj":40.000638516547376,"engagementSEIrank":195,"voiceSEI":0.15456288837097776,"voiceSEIadj":40.09273773302259,"voiceSEIrank":200},"scoped":{"SEI":0.4707210194088515,"SEIadj":40.28243261164531,"SEIrank":186,"compCharisma":0,"compInfluence":0,"compEva":0.4707210194088515,"audienceSEI":4.133400865737574,"audienceSEIadj":52.066700432868785,"audienceSEIrank":124,"engagementSEI":0.027208160243313212,"engagementSEIadj":40.01632489614599,"engagementSEIrank":180,"voiceSEI":0.6323492655344082,"voiceSEIadj":40.37940955932064,"voiceSEIrank":185}},"facebook":{"non_scoped":{"SEI":0.015683875850229217,"SEIadj":50.007841937925114,"SEIrank":155,"audienceSEI":0.12510216858250875,"audienceSEIadj":50.06255108429126,"audienceSEIrank":139,"engagementSEI":0.0000406388756361,"engagementSEIadj":50.000020319437816,"engagementSEIrank":150,"voiceSEI":0.010497585555322275,"voiceSEIadj":50.005248792777664,"voiceSEIrank":150},"scoped":{"SEI":0.18224480848595762,"SEIadj":50.09112240424298,"SEIrank":141,"audienceSEI":1.6165616814488661,"audienceSEIadj":50.808280840724436,"audienceSEIrank":124,"engagementSEI":0.0038265956904028984,"engagementSEIadj":50.0019132978452,"engagementSEIrank":138,"voiceSEI":0.06097560975609756,"voiceSEIadj":50.03048780487805,"voiceSEIrank":139}},"twitter":{"non_scoped":{"SEI":0.21649079537548999,"SEIadj":40.12989447722529,"SEIrank":182,"audienceSEI":1.013225717957233,"audienceSEIadj":50.50661285897861,"audienceSEIrank":119,"engagementSEI":0.057798594655522124,"engagementSEIadj":40.03467915679332,"engagementSEIrank":175,"voiceSEI":0.268296889288178,"voiceSEIadj":40.160978133572904,"voiceSEIrank":190},"scoped":{"SEI":0.9687021540365846,"SEIadj":40.58122129242195,"SEIrank":167,"audienceSEI":4.8162796084520805,"audienceSEIadj":52.40813980422604,"audienceSEIrank":105,"engagementSEI":0.3688744388128161,"engagementSEIadj":40.22132466328769,"engagementSEIrank":162,"voiceSEI":0.8858317663456224,"voiceSEIadj":40.53149905980737,"voiceSEIrank":174}},"instagram":{"non_scoped":{"SEI":0,"SEIadj":0,"SEIrank":53,"audienceSEI":0,"audienceSEIadj":0,"audienceSEIrank":53,"engagementSEI":0,"engagementSEIadj":0,"engagementSEIrank":48,"voiceSEI":0,"voiceSEIadj":0,"voiceSEIrank":48},"scoped":{"SEI":0,"SEIadj":0,"SEIrank":46,"audienceSEI":0,"audienceSEIadj":0,"audienceSEIrank":46,"engagementSEI":0,"engagementSEIadj":0,"engagementSEIrank":41,"voiceSEI":0,"voiceSEIadj":0,"voiceSEIrank":41}},"influence":{"instagram":{"scope":"individual","ratio":0,"calculated":false},"combined":{"ratio":0.2,"bottom":false,"scope":"individual","calculated":true},"facebook":{"ratio":0.03,"bottom":true,"scope":"individual","calculated":true},"twitter":{"ratio":0.16,"bottom":false,"scope":"individual","calculated":true}},"charisma":{"instagram":{"scope":"individual","ratio":0,"calculated":false},"combined":{"ratio":0.12,"bottom":true,"scope":"individual","calculated":true},"facebook":{"ratio":0.15,"bottom":false,"scope":"individual","calculated":true},"twitter":{"ratio":0.47,"bottom":false,"scope":"individual","calculated":true}}},"scope":"individual"}}